Workbook
Name _ccVersion: 1.74
Name _scenchg_count: 1
Name africa: #REF!
Name africa: #REF!
Name africa: #REF!
Name africa: #REF!
Name africa: #REF!
Name africaCountries: #REF!
Name africaCountries: #REF!
Name africaCountries: #REF!
Name africaCountries: #REF!
Name africaCountries: #REF!
Name allRegions: #REF!
Name allRegions: #REF!
Name allRegions: #REF!
Name allRegions: #REF!
Name allRegions: #REF!
Name americaRegion: #REF!
Name americaRegion: #REF!
Name americaRegion: #REF!
Name americaRegion: #REF!
Name americaRegion: #REF!
Name americas: #REF!
Name americas: #REF!
Name americas: #REF!
Name americas: #REF!
Name americas: #REF!
Name americasStates: #REF!
Name americasStates: #REF!
Name americasStates: #REF!
Name americasStates: #REF!
Name americasStates: #REF!
Name AppVersion: #REF!
Name AppVersion: #REF!
Name AppVersion: #REF!
Name AppVersion: #REF!
Name AppVersion: #REF!
Name asiaPacific: #REF!
Name asiaPacific: #REF!
Name asiaPacific: #REF!
Name asiaPacific: #REF!
Name asiaPacific: #REF!
Name asiaPacificExJapan: #REF!
Name asiaPacificExJapan: #REF!
Name asiaPacificExJapan: #REF!
Name asiaPacificExJapan: #REF!
Name asiaPacificExJapan: #REF!
Name asiaPacificExJapanCountries: #REF!
Name asiaPacificExJapanCountries: #REF!
Name asiaPacificExJapanCountries: #REF!
Name asiaPacificExJapanCountries: #REF!
Name asiaPacificExJapanCountries: #REF!
Name asiaPacificRegion: #REF!
Name asiaPacificRegion: #REF!
Name asiaPacificRegion: #REF!
Name asiaPacificRegion: #REF!
Name asiaPacificRegion: #REF!
Name asiaPacificStates: #REF!
Name asiaPacificStates: #REF!
Name asiaPacificStates: #REF!

Sheet Cover
C4: Greater China Technology Hardware
CU5: 29.902
I7: Contacts | M7: Phone | O7: Email
I8: Greater China Technology Hardware
I9: Howard Kao | M9: +886-2730-2989 | O9: howard.kao@morganstanley.com
I10: Sharon Shih | M10: +886-2730-2865 | O10: sharon.shih@morganstanley.com
C14: Disclaimer
C15: The information and opinions in Morgan Stanley Research were prepared or are disseminated by Morgan Stanley Asia Limited (which accepts the responsibility for its contents) and/or Morgan Stanley Asia (Singapore) Pte. (Registration number 199206298Z) and/or Morgan Stanley Asia (Singapore) Securities Pte Ltd (Registration number 200008434H), regulated by the Monetary Authority of Singapore (which accepts legal responsibility for its contents and should be contacted with respect to any matters arising from, or in connection with, Morgan Stanley Research), and/or Morgan Stanley Taiwan Limited and/or Morgan Stanley & Co International plc, Seoul Branch, and/or Morgan Stanley Australia Limited (A.B.N. 67 003 734 576, holder of Australian financial services license No. 233742, which accepts responsibility for its contents), and/or Morgan Stanley Wealth Management Australia Pty Ltd (A.B.N. 19 009 145 555, holder of Australian financial services license No. 240813, which accepts responsibility for its contents), and/or Morgan Stanley India Company Private Limited, regulated by the Securities and Exchange Board of India (“SEBI”) and holder of licenses as a Research Analyst (SEBI Registration No. INH000001105); Stock Broker (BSE Registration No. INB011054237 and NSE Registration No. INB/INF231054231), Merchant Banker (SEBI Registration No. INM000011203), and depository participant with National Securities Depository Limited (SEBI Registration No. IN-DP-NSDL-372-2014) which accepts the responsibility for its contents and should be contacted with respect to any matters arising from, or in connection with, Morgan Stanley Research, and/or PT Morgan Stanley Asia Indonesia and their affiliates (collectively, "Morgan Stanley"). For important disclosures, stock price charts and equity rating histories regarding companies that are the subject of this report, please see the Morgan Stanley Research Disclosure Website at www.morganstanley.com/researchdisclosures, or contact your investment representative or Morgan Stanley Research at 1585 Broadway, (Attention: Research Management), New York, NY, 10036 USA. For valuation methodology and risks associated with any recommendation, rating or price target referenced in this research report, please contact the Client Support Team as follows: US/Canada +1 800 303-2495; Hong Kong +852 2848-5999; Latin America +1 718 754-5444 (U.S.); London +44 (0)20-7425-8169; Singapore +65 6834-6860; Sydney +61 (0)2-9770-1505; Tokyo +81 (0)3-6836-9000. Alternatively you may contact your investment representative or Morgan Stanley Research at 1585 Broadway, (Attention: Research Management), New York, NY 10036 USA.
CS16: =+(257901+8807)-SUM(CP16:CR16) -> 266708
CS17: =+(524788+11152)-SUM(CP17:CR17) -> 535940
T22: Check | U22: +'ODM share analysis'!R[164]C[-3]*1000-'GB200-300 Tracker (2025)'!R[3]C
CO25: =+CO31/CO16*1000 -> #DIV/0! | CS25: =+CS31/CS16*1000 -> 0
CO26: =+CO32/CO17*1000 -> #DIV/0! | CS26: =+CS32/CS17*1000 -> 0
C27: Analyst Certification
C28: The following analysts hereby certify that their views about the companies and their securities discussed in this report are accurately expressed and that they have not received and will not receive direct or indirect compensation in exchange for expressing specific recommendations or views in this report: Howard Kao. Unless otherwise stated, the individuals listed on the cover page of this report are research analysts. Important US Regulatory Disclosures on Subject Companies The equity research analysts or strategists principally responsible for the preparation of Morgan Stanley Research have received compensation based upon various factors, including quality of research, investor client feedback, stock picking, competitive factors, firm revenues and overall investment banking revenues. Equity Research analysts' or strategists' compensation is not linked to investment banking or capital markets transactions performed by Morgan Stanley or the profitability or revenues of particular trading desks. Morgan Stanley and its affiliates do business that relates to companies/instruments covered in Morgan Stanley Research, including market making, providing liquidity, fund management, commercial banking, extension of credit, investment services and investment banking. Morgan Stanley sells to and buys from customers the securities/instruments of companies covered in Morgan Stanley Research on a principal basis. Morgan Stanley may have a position in the debt of the Company or instruments discussed in this report. Morgan Stanley trades or may trade as principal in the debt securities (or in related derivatives) that are the subject of the debt research report. Certain disclosures listed above are also for compliance with applicable regulations in non-US jurisdictions. | CL28: 0.453 | CM28: 0.6 | CN28: 0.8 | CO28: =+CO25/CN25-1 -> #DIV/0! | CP28: -0.569 | CQ28: -0.36 | CR28: -0.15 | CS28: =+CS25/CR25-1 -> #DIV/0!
CL29: 0.122 | CM29: 0.5 | CN29: 0.44 | CO29: =+CO26/CN26-1 -> #DIV/0! | CP29: -0.266 | CQ29: -0.2 | CR29: -0.1 | CS29: =+CS26/CR26-1 -> #DIV/0!
Q158: 345.5
D169: 8.05
P178: 0.4 | Q178: 1.26

Sheet Nvidia Rack Layout
B2: RU | C2: GB200 NVL72 | E2: GB300 NVL72 | G2: VR200 NVL72 | I2: VR200 NVL72 w/ CPX | K2: VR200 CPX | M2: Groq LPX
B3: 48 | C3: MGMT SW | E3: MGMT SW | G3: MGMT SW | I3: MGMT SW | K3: MGMT SW | M3: MGMT SW
B4: 47
B5: 46
B6: 45
B7: 44 | G7: 3U Power Shelf - 110kW | I7: 3U Power Shelf - 110kW | K7: 3U Power Shelf - 110kW
B8: 43
B9: 42 | E9: 1U Power Shelf - 33kW | M9: 1U Power Shelf - 90kW
B10: 41 | C10: 1U Power Shelf - 33kW | E10: 1U Power Shelf - 33kW | G10: 3U Power Shelf - 110kW | I10: 3U Power Shelf - 110kW | K10: 3U Power Shelf - 110kW | M10: 1U Power Shelf - 90kW
B11: 40 | C11: 1U Power Shelf - 33kW | E11: 1U Power Shelf - 33kW | M11: Filler panel
B12: 39 | C12: 1U Power Shelf - 33kW | E12: 1U Power Shelf - 33kW | M12: Compute Tray - 16x Groq 3 LPU, 2x GPFA, 1x CPU
B13: 38 | C13: Filler panel | E13: Filler panel | G13: Filler panel | I13: Filler panel | K13: Filler panel
B14: 37 | C14: Compute Tray - CX7 - w/BF3 | E14: Compute Tray - CX8 - w/ BF3 | G14: Compute Tray - CX9 - w/BF4 | I14: Compute Tray - CX9 - w/BF4 | K14: Compute Tray - 2x Vera, 8x CPX | M14: Compute Tray - 16x Groq 3 LPU, 2x GPFA, 1x CPU
B15: 36 | C15: Compute Tray - CX7 - w/BF3 | E15: Compute Tray - CX8 - w/ BF3 | G15: Compute Tray - CX9 - w/BF4 | I15: Compute Tray - CX9 - w/BF4 | K15: Compute Tray - 2x Vera, 8x CPX
B16: 35 | C16: Compute Tray - CX7 - w/BF3 | E16: Compute Tray - CX8 - w/ BF3 | G16: Compute Tray - CX9 - w/BF4 | I16: Compute Tray - CX9 - w/BF4 | K16: Compute Tray - 2x Vera, 8x CPX | M16: Compute Tray - 16x Groq 3 LPU, 2x GPFA, 1x CPU
B17: 34 | C17: Compute Tray - CX7 - w/BF3 | E17: Compute Tray - CX8 - w/ BF3 | G17: Compute Tray - CX9 - w/BF4 | I17: Compute Tray - CX9 - w/BF4 | K17: Compute Tray - 2x Vera, 8x CPX
B18: 33 | C18: Compute Tray - CX7 - w/BF3 | E18: Compute Tray - CX8 - w/ BF3 | G18: Compute Tray - CX9 - w/BF4 | I18: Compute Tray - CX9 - w/BF4 | K18: Compute Tray - 2x Vera, 8x CPX | M18: Compute Tray - 16x Groq 3 LPU, 2x GPFA, 1x CPU
B19: 32 | C19: Compute Tray - CX7 - w/BF3 | E19: Compute Tray - CX8 - w/ BF3 | G19: Compute Tray - CX9 - w/BF4 | I19: Compute Tray - CX9 - w/BF4 | K19: Compute Tray - 2x Vera, 8x CPX
B20: 31 | C20: Compute Tray - CX7 - w/BF3 | E20: Compute Tray - CX8 - w/ BF3 | G20: Compute Tray - CX9 - w/BF4 | I20: Compute Tray - CX9 - w/BF4 | K20: Compute Tray - 2x Vera, 8x CPX | M20: Compute Tray - 16x Groq 3 LPU, 2x GPFA, 1x CPU
B21: 30 | C21: Compute Tray - CX7 - w/BF3 | E21: Compute Tray - CX8 - w/ BF3 | G21: Compute Tray - CX9 - w/BF4 | I21: Compute Tray - CX9 - w/BF4 | K21: Compute Tray - 2x Vera, 8x CPX
B22: 29 | C22: Compute Tray - CX7 - w/BF3 | E22: Compute Tray - CX8 - w/ BF3 | G22: Compute Tray - CX9 - w/BF4 | I22: Compute Tray - CX9 - w/BF4 | K22: Compute Tray - 2x Vera, 8x CPX | M22: Compute Tray - 16x Groq 3 LPU, 2x GPFA, 1x CPU
B23: 28 | C23: Compute Tray - CX7 - w/BF3 | E23: Compute Tray - CX8 - w/ BF3 | G23: Compute Tray - CX9 - w/BF4 | I23: Compute Tray - CX9 - w/BF4 | K23: Compute Tray - 2x Vera, 8x CPX
B24: 27 | C24: NV Switch Tray | E24: NV Switch Tray | G24: NV Switch Tray | I24: NV Switch Tray | K24: Compute Tray - 2x Vera, 8x CPX | M24: Compute Tray - 16x Groq 3 LPU, 2x GPFA, 1x CPU
B25: 26 | C25: NV Switch Tray | E25: NV Switch Tray | G25: NV Switch Tray | I25: NV Switch Tray | K25: Compute Tray - 2x Vera, 8x CPX
B26: 25 | C26: NV Switch Tray | E26: NV Switch Tray | G26: NV Switch Tray | I26: NV Switch Tray | K26: Compute Tray - 2x Vera, 8x CPX | M26: Compute Tray - 16x Groq 3 LPU, 2x GPFA, 1x CPU
B27: 24 | C27: NV Switch Tray | E27: NV Switch Tray | G27: NV Switch Tray | I27: NV Switch Tray | K27: Compute Tray - 2x Vera, 8x CPX
B28: 23 | C28: NV Switch Tray | E28: NV Switch Tray | G28: NV Switch Tray | I28: NV Switch Tray | K28: Compute Tray - 2x Vera, 8x CPX | M28: Compute Tray - 16x Groq 3 LPU, 2x GPFA, 1x CPU
B29: 22 | C29: NV Switch Tray | E29: NV Switch Tray | G29: NV Switch Tray | I29: NV Switch Tray | K29: Compute Tray - 2x Vera, 8x CPX
B30: 21 | C30: NV Switch Tray | E30: NV Switch Tray | G30: NV Switch Tray | I30: NV Switch Tray | K30: Compute Tray - 2x Vera, 8x CPX | M30: Compute Tray - 16x Groq 3 LPU, 2x GPFA, 1x CPU
B31: 20 | C31: NV Switch Tray | E31: NV Switch Tray | G31: NV Switch Tray | I31: NV Switch Tray | K31: Compute Tray - 2x Vera, 8x CPX
B32: 19 | C32: NV Switch Tray | E32: NV Switch Tray | G32: NV Switch Tray | I32: NV Switch Tray | K32: Drip Tray | M32: Compute Tray - 16x Groq 3 LPU, 2x GPFA, 1x CPU
B33: 18 | C33: Compute Tray - CX7 - w/BF3 | E33: Compute Tray - CX8 - w/ BF3 | G33: Compute Tray - CX9 - w/BF4 | I33: Compute Tray - CX9 - w/BF4
B34: 17 | C34: Compute Tray - CX7 - w/BF3 | E34: Compute Tray - CX8 - w/ BF3 | G34: Compute Tray - CX9 - w/BF4 | I34: Compute Tray - CX9 - w/BF4 | M34: Compute Tray - 16x Groq 3 LPU, 2x GPFA, 1x CPU
B35: 16 | C35: Compute Tray - CX7 - w/BF3 | E35: Compute Tray - CX8 - w/ BF3 | G35: Compute Tray - CX9 - w/BF4 | I35: Compute Tray - CX9 - w/BF4
B36: 15 | C36: Compute Tray - CX7 - w/BF3 | E36: Compute Tray - CX8 - w/ BF3 | G36: Compute Tray - CX9 - w/BF4 | I36: Compute Tray - CX9 - w/BF4 | M36: Compute Tray - 16x Groq 3 LPU, 2x GPFA, 1x CPU
B37: 14 | C37: Compute Tray - CX7 - w/BF3 | E37: Compute Tray - CX8 - w/ BF3 | G37: Compute Tray - CX9 - w/BF4 | I37: Compute Tray - CX9 - w/BF4
B38: 13 | C38: Compute Tray - CX7 - w/BF3 | E38: Compute Tray - CX8 - w/ BF3 | G38: Compute Tray - CX9 - w/BF4 | I38: Compute Tray - CX9 - w/BF4 | M38: Compute Tray - 16x Groq 3 LPU, 2x GPFA, 1x CPU
B39: 12 | C39: Compute Tray - CX7 - w/BF3 | E39: Compute Tray - CX8 - w/ BF3 | G39: Compute Tray - CX9 - w/BF4 | I39: Compute Tray - CX9 - w/BF4
B40: 11 | C40: Compute Tray - CX7 - w/BF3 | E40: Compute Tray - CX8 - w/ BF3 | G40: Compute Tray - CX9 - w/BF4 | I40: Compute Tray - CX9 - w/BF4 | M40: Compute Tray - 16x Groq 3 LPU, 2x GPFA, 1x CPU
B41: 10 | C41: Drip Tray | E41: Drip Tray | G41: Drip Tray | I41: Drip Tray
B42: 9 | C42: 1U Power Shelf - 33kW | E42: 1U Power Shelf - 33kW | G42: 3U Power Shelf - 110kW | I42: 3U Power Shelf - 110kW | M42: Compute Tray - 16x Groq 3 LPU, 2x GPFA, 1x CPU
B43: 8 | C43: 1U Power Shelf - 33kW | E43: 1U Power Shelf - 33kW
B44: 7 | C44: 1U Power Shelf - 33kW | E44: 1U Power Shelf - 33kW | M44: Filler panel
B45: 6 | E45: 1U Power Shelf - 33kW | G45: 3U Power Shelf - 110kW | I45: 3U Power Shelf - 110kW | M45: 1U Power Shelf - 90kW
B46: 5 | M46: 1U Power Shelf - 90kW
B47: 4
B48: 3
B49: 2
B50: 1
C52: Total Power Capacity (kW) | E52: Total Power Capacity (kW) | G52: Total Power Capacity (kW)
C53: 198 | E53: 264 | G53: 440
C54: Total Power Usage (kW) | E54: Total Power Usage (kW) | G54: Total Power Usage (kW)
C55: =+'[6]NVL72 Power Budget'!E29/1000 -> 131.6736 | E55: =+'[6]NVL72 Power Budget'!J29/1000 -> 146.3364 | G55: =+'[6]NVL72 Power Budget'!O29/1000 -> 233.5176

Sheet GPU Roadmap
B2: Nvidia Client version | C2: 2 | D2: 3 | E2: 4 | F2: 5 | G2: 6 | H2: 7 | I2: 8 | J2: 9
B3: NVIDIA | C3: A100 | D3: H100 | E3: H200 | F3: B200 | G3: GB200 NVL72 | H3: HGX B200A B200A Ultra (PHASED OUT) | I3: MGX GB300A NVL36 (RENAMED FROM GB200A Ultra) | J3: GB300 NVL72 (RENAMED FROM GB200 Ultra) | K3: VR200 NVL144 | L3: VR200 NVL144 CPX | M3: VR300
B4: Launch timing | C4: 2Q20 | D4: 4Q22 | E4: 2Q24 | F4: 1Q25 | G4: 4Q24 | H4: 1Q25 | I4: 3Q25 | J4: 3Q25 | K4: 2H26 | L4: End of 2026 | M4: 2H27
B5: CPU | C5: x86 | D5: x86 | E5: x86 | F5: x86 | G5: Grace | H5: x86 | I5: Grace | J5: Grace | K5: Vera | L5: Vera | M5: Vera
B6: Back-end | C6: CoWoS-S | D6: CoWoS-S | E6: CoWoS-S | F6: CoWoS-L | G6: CoWoS-L | H6: CoWoS-S | I6: CoWoS-S | J6: CoWoS-L | K6: CoWoS-L | L6: CoWoS-L | M6: CoWoS-L
B7: GPU Cooling | C7: Air | D7: Air | E7: Air & Liquid | F7: Air & Liquid | G7: Liquid | H7: Air & Liquid | I7: Air | J7: Liquid | K7: Liquid | L7: Liquid | M7: Liquid
B8: GPU Max TDP | C8: 400W | D8: 700W | E8: 700W | F8: 1,000W | G8: 1,200W | H8: 700W | 1,000W | I8: 700W | J8: 1,400W | K8: 2,300W | L8: 800W | M8: 3,600W
B9: Product Form Factor | C9: DGX/HGX 8x GPU PCIe | D9: DGX/HGX 8x GPU PCIe | E9: DGX/HGX 8x GPU PCIe | F9: DGX/HGX 8x GPU PCIe | G9: GB 2:4 board NVSwitch tray NVL backplane | H9: HGX 8x GPU | I9: GB 1:4 board (9x MGX) NVSwitch tray NVL backplane | J9: GB 2:4 board NVSwitch tray NVL backplane | K9: Oberon VR 2:4 board NVSwitch tray NVL backplane | L9: Oberon VR 2:4 board NVSwitch tray NVL backplane | M9: Kyber
B10: GPU Memory | C10: 80GB | HBM2e | 4/8H | D10: 80/96GB | HBM2e/3 | 8H | E10: 141GB | HBM3e | 8H | F10: 192GB | HBM3e | 8H | G10: 192GB | HBM3e | 8H | H10: 144GB | HBM3e | 12H | I10: 144GB | HBM3e | 12H | J10: 288GB | HBM3e | 8/12H | K10: 288GB | HBM4 | 8H | L10: 128GB GDDR7 | M10: 1TB | HBM4e | 16H
B11: HBM Vendor | C11: Hynix | D11: Hynix | E11: Hynix/Micron | F11: Hynix/Micron/Samsung | G11: Hynix/Micron/Samsung | H11: Hynix/Micron/Samsung | I11: Hynix/Micron/Samsung | J11: Hynix/Micron/Samsung | K11: Hynix/Micron/Samsung | L11: Hynix/Micron/Samsung | M11: Hynix/Micron/Samsung
B12: NVLink B/W per GPU | C12: 600GB/s | D12: 900GB/s | E12: 900GB/s | F12: 1,800 GB/s | G12: 1,800 GB/s | H12: 1,800 GB/s | I12: 1,800 GB/s | J12: 1,800 GB/s | K12: 3,600 GB/s | L12: 3,600 GB/s | M12: 3,600 GB/s
B13: CPU-GPU Interface | C13: 64 GB/s PCIe4 | D13: 128 GB/s PCIe5 | E13: 128 GB/s PCIe5 | F13: 128 GB/s PCIe5 | G13: 450 GB/s C2C | H13: 128 GB/s PCIe5 | I13: 64 GB/s PCIe5 | J13: 450 GB/s C2C | K13: 1.8TB/s C2C | L13: 1.8TB/s C2C | M13: 1.8TB/s C2C
B14: Network Adapter | C14: 200G CX6 | BF2 | D14: 400G CX7 | BF3 | E14: 400G CX7 | BF3 | F14: 400G CX7 | BF3 | G14: 400G CX7 | BF3 | H14: 400G CX7 | BF3 | I14: 800G CX8 | J14: 800G CX8 | K14: 1,600G CX9 | L14: 1,600G CX9 | M14: 1,600G CX9
B16: ABF/CCL/PCB (client version)
B17: NVIDIA | C17: A100 | D17: H100 | E17: H200 | F17: B200 | G17: GB200 NVL72 | H17: HGX B200A B200A Ultra (PHASED OUT) | I17: MGX GB300A NVL36 (RENAMED FROM GB200A Ultra) | J17: GB300 NVL72 (RENAMED FROM GB200 Ultra) | K17: VR200 NVL144 | L17: VR200 NVL144 CPX | M17: VR300
B18: ABF Substrate
B19: Substrate size | C19: 55mm x 55mm | D19: 55mm x 58mm | E19: 55mm x 58mm | F19: 73mm x 81mm | G19: 73mm x 81mm | H19: NA | I19: NA | J19: 73mm x 81mm | K19: 83mm x 97mm | L19: 83mm x 97mm | M19: 83mm x 97mm
B20: Layer count | C20: 16L | D20: 12L | E20: 12L | F20: 14L | G20: 14L | H20: NA | I20: NA | J20: 14L | K20: 18L | L20: 18L | M20: 18L
B21: Supplier | C21: Ibiden | D21: Ibiden | E21: Ibiden | F21: Ibiden/Unimicron | G21: Ibiden/Unimicron | H21: Kinsus | I21: Ibiden/Unimicron | J21: Ibiden/Unimicron | K21: Ibiden/Unimicron | L21: Ibiden/Unimicron | M21: Ibiden/Unimicron
B22: OCP Accelerator Module (OAM)
B23: CCL Spec. | C23: 0 | D23: Very low-loss (M6), Ultra low-loss (M7) | E23: Very low-loss (M6), Ultra low-loss (M7) | F23: Extreme low-loss (M8) | G23: Extreme low-loss (M8) | H23: Extreme low-loss (M8) | I23: Extreme low-loss (M8) | J23: Extreme low-loss (M8) | K23: Extreme low-loss (M8) + Low-loss (M4) | L23: Extreme low-loss (M8) + Low-loss (M4) | M23: M9 (?)
B24: CCL supplier | C24: 0 | D24: EMC | E24: EMC | F24: Doosan, EMC | G24: Doosan, EMC | H24: Doosan, EMC | I24: Doosan, EMC | J24: Doosan, EMC | K24: Doosan | L24: Doosan | M24: ?
B25: PCB Spec. | C25: 0 | D25: 18L HDI | E25: 18L HDI | F25: 18L HDI | G25: 22L HDI | H25: ? | I25: ? | J25: 22L HDI | K25: 26L HDI | L25: 26L HDI | M25: 0
B26: PCB Supplier | C26: 0 | D26: UMTC, ISU, TTM, WUS | E26: UMTC, ISU, TTM, WUS | F26: UMTC, ISU, TTM, VGT | G26: VGT, UMTC | H26: UMTC, ISU, TTM, WUS, VGT | I26: UMTC, ISU, TTM, WUS, VGT | J26: VGT, UMTC | K26: VGT, UMTC, ZDT, Dynamic | L26: VGT, UMTC, ZDT, Dynamic | M26: 0
B27: Universal Baseboard (UBB)
B28: CCL Spec. | C28: 0 | D28: Ultra low-loss (M7) | E28: Ultra low-loss (M7) | F28: Extreme low-loss (M8) | G28: NA | H28: 0 | I28: 0 | J28: NA | K28: NA | L28: NA | M28: 0
B29: CCL supplier | C29: EMC | D29: EMC, TUC | E29: EMC, TUC | F29: Doosan, EMC, TUC | G29: NA | H29: 0 | I29: 0 | J29: NA | K29: NA | L29: NA | M29: 0
B30: PCB Spec. | C30: 0 | D30: 26-30L | E30: 26-30L | F30: 28-30L | G30: NA | H30: 0 | I30: 0 | J30: NA | K30: NA | L30: NA | M30: 0
B31: PCB Supplier | C31: 0 | D31: WUS, TTM, ISU | E31: WUS, TTM, ISU | F31: WUS, TTM, ISU, UMTC | G31: NA | H31: 0 | I31: 0 | J31: NA | K31: NA | L31: NA | M31: 0
B32: Switch board
B33: CCL Spec. | C33: Ultra low-loss (M7) | D33: Very low-loss (M6), Ultra low-loss (M7) | E33: Very low-loss (M6), Ultra low-loss (M7) | F33: Ultra low-loss (M7), Extreme low-loss (M8) | G33: Extreme low-loss (M8) | H33: Extreme low-loss (M8) | I33: Extreme low-loss (M8) | J33: Extreme low-loss (M8) | K33: Extreme low-loss (M8) | L33: M8.5 or beyond (M9) | M33: 0
B34: CCL supplier | C34: 0 | D34: EMC, TUC | E34: EMC, TUC | F34: EMC, TUC, Doosan | G34: EMC | H34: EMC, Doosan | I34: EMC, Doosan | J34: EMC, Shengyi | K34: EMC, Shengyi | L34: EMC, Doosan, Shengyi | M34: 0
B35: PCB Spec. | C35: 0 | D35: 26-28L | E35: 26-28L | F35: 28-30L | G35: 24L PTH | H35: ? | I35: ? | J35: 24L PTH | K35: 32L PTH | L35: 26L HDI or PTH ? | M35: 0
B36: PCB Supplier | C36: 0 | D36: WUS, TTM, GCE, ISU | E36: WUS, TTM, GCE, ISU | F36: WUS, TTM, GCE, ISU | G36: WUS, TTM, VGT | H36: UMTC, WUS, TTM, GCE, ISU | I36: UMTC, WUS, TTM, GCE, ISU | J36: VGT, TTM, Kinwon | K36: VGT, WUS, TTM | L36: WUS, VGT, UMTC, TTM | M36: 0
B37: Motherboard
B38: CCL Spec. | C38: Very low-loss (M6) | D38: Very low-loss (M6) | E38: Very low-loss (M6) | F38: Very low-loss (M6) | G38: NA | H38: 0 | I38: 0 | J38: NA | K38: NA | L38: NA | M38: 0
B39: CCL supplier | C39: EMC, TUC, ITEQ, Panasonic | D39: EMC, TUC, ITEQ, Panasonic | E39: EMC, TUC, ITEQ, Panasonic | F39: EMC, TUC, ITEQ, Panasonic | G39: NA | H39: 0 | I39: 0 | J39: NA | K39: NA | L39: NA | M39: 0
B40: PCB Spec. | C40: 16-18L | D40: 16-18L | E40: 16-18L | F40: 16-20L | G40: NA | H40: 0 | I40: 0 | J40: NA | K40: NA | L40: NA | M40: 0
B41: PCB Supplier | C41: GCE, WUS, TTM, ISU, Tripod | D41: GCE, WUS, TTM, ISU, Tripod | E41: GCE, WUS, TTM, ISU, Tripod | F41: GCE, WUS, TTM, ISU, Tripod | G41: NA | H41: 0 | I41: 0 | J41: NA | K41: NA | L41: NA | M41: 0
B42: Midplane PCB
B43: CCL Spec. | C43: =+#REF! -> #REF! | D43: NA | E43: NA | F43: NA | G43: NA | H43: NA | I43: NA | J43: NA | K43: Beyond extreme low-loss (M9) | L43: NA | M43: NA
B44: CCL supplier | C44: =+#REF! -> #REF! | D44: NA | E44: NA | F44: NA | G44: NA | H44: NA | I44: NA | J44: NA | K44: EMC | L44: NA | M44: NA
B45: PCB Spec. | C45: =+#REF! -> #REF! | D45: NA | E45: NA | F45: NA | G45: NA | H45: NA | I45: NA | J45: NA | K45: 44L PTH | L45: NA | M45: NA
B46: PCB Supplier | C46: =+#REF! -> #REF! | D46: NA | E46: NA | F46: NA | G46: NA | H46: NA | I46: NA | J46: NA | K46: VGT, WUS | L46: NA | M46: NA
B47: Orchid Module / BlueField Module
B48: CCL Spec. | C48: =+#REF! -> #REF! | D48: NA | E48: NA | F48: NA | G48: NA | H48: NA | I48: NA | J48: NA | K48: Extreme low-loss (M8) | L48: NA | M48: NA
B49: CCL supplier | C49: =+#REF! -> #REF! | D49: NA | E49: NA | F49: NA | G49: NA | H49: NA | I49: NA | J49: NA | K49: EMC | L49: NA | M49: NA
B50: PCB Spec. | C50: =+#REF! -> #REF! | D50: NA | E50: NA | F50: NA | G50: NA | H50: NA | I50: NA | J50: NA | K50: 20L PTH | L50: NA | M50: NA
B51: PCB Supplier | C51: =+#REF! -> #REF! | D51: NA | E51: NA | F51: NA | G51: NA | H51: NA | I51: NA | J51: NA | K51: WUS, VGT, TTM, UMTC | L51: NA | M51: NA
B54: AMD Client version | C54: 2 | D54: 3 | E54: 4 | F54: 5 | G54: 6 | H54: 7 | I54: 8 | J54: 9
B55: AMD | C55: MI250X | D55: MI300A | E55: MI300X | F55: MI325X | G55: MI350X | H55: MI355X | I55: MI375X | J55: MI405X
B56: Launch timing | C56: 4Q21 | D56: 4Q23 | E56: 4Q23 | F56: 4Q24 | G56: 3Q25 | H56: 3Q25 | I56: 4Q25 | J56: 3Q26
B57: CPU | C57: x86 | D57: x86 | E57: x86 | F57: x86 | G57: x86 | H57: 0 | I57: 0 | J57: 0
B58: Back-end | C58: SoIC + CoWoS-S | D58: SoIC + CoWoS-S | E58: SoIC + CoWoS-S | F58: SoIC + CoWoS-S | G58: SoIC + CoWoS-S | H58: SoIC + CoWoS-S | I58: SoIC + CoWoS-S | J58: SoIC + CoWoS-S
B59: GPU Cooling | C59: Air | D59: Air | E59: Air | F59: Air | G59: Air | H59: 0 | I59: 0 | J59: 0
B60: GPU Max TDP | C60: 560W | D60: 760W | E60: 750W | F60: 750W | G60: 750W | H60: 1,000W | I60: 1,200W | J60: 0
B61: Product Form Factor | C61: 4x GPU | D61: 4x APU | E61: 8x GPU | F61: 8x GPU | G61: N/A | H61: 0 | I61: 0 | J61: 0
B62: GPU Memory | C62: 128GB | HBM2e | D62: 128GB | HBM3 | E62: 192GB | HBM3 | F62: 288GB | HBM3e | G62: 288GB | HBM3e | H62: 288GB | I62: 288GB | J62: HBM4
B63: HBM Vendor | C63: Samsung | D63: Samsung | E63: Samsung | F63: N/A | G63: N/A | H63: 0 | I63: 0 | J63: 0
B64: B/W per GPU | C64: 200GB/s | D64: 384GB/s | E64: 896GB/s | F64: N/A | G64: N/A | H64: 0 | I64: 0 | J64: 0
B65: CPU-GPU Interface | C65: 64 GB/s PCIe4 | D65: N/A | E65: 128 GB/s PCIe5 | F65: 128 GB/s PCIe5 | G65: 128 GB/s PCIe5 | H65: 0 | I65: 0 | J65: 0

Sheet ODM share analysis
B1: Joe's numbers (k units) | D1: 2023 | E1: 2024 | F1: 2025 | G1: 2026 | H1: 2027
B2: A100 | D2: 265.38269 | E2: 0 | F2: 0 | G2: 0 | H2: 0
B3: H100/200 | D3: 1249.2717 | E3: 3842.6 | F3: 560.9 | G3: 0 | H3: 0
B4: B200/300 | D4: 0 | E4: 363.2 | F4: 4279.8 | G4: 3498 | H4: 0
B5: R100/200 | D5: 0 | E5: 0 | F5: 0 | G5: 2262.3 | H5: 3620.2
B6: X100 | G6: 54.6 | H6: 1810
B7: Others | D7: 267.6238 | E7: 958 | F7: 446.5 | G7: 864.2 | H7: 950.5
B9: Nvidia AI server unit assumption | Y9: ODM share
B10: k units | C10: 2022 | D10: 2023 | E10: 2024 | F10: 2025 | G10: 2026 | H10: 2027 | J10: 2023-26 CAR | Y10: Mix | Z10: 2023 | AA10: 2024
B11: HGX+DGX (8x GPU) | C11: =+SUM(C13:C18) -> 104.5 | D11: =+D12+D18 -> 189.3318 | E11: =+E12+E18 -> 525.725 | F11: =+F12+F18 -> 161.1125 | G11: =+G12+G18 -> 97.825 | H11: =+H12+H18 -> 70 | J11: =+(#REF!/#REF!)^(1/3)-1 -> #REF! | Y11: =+Y83 -> Quanta | Z11: =+VLOOKUP(Y11,$Y$83:$Z$93,2,FALSE) -> 0.084507725 | AA11: =+VLOOKUP(Y11,$Y$124:$Z$137,2,FALSE) -> 0.13124733
B12: HGX | D12: =SUM(D13:D15) -> 186.3318 | E12: =SUM(E13:E15) -> 512.725 | F12: =SUM(F13:F16) -> 154.1125 | G12: =SUM(G13:G17) -> 96.825 | H12: =SUM(H13:H17) -> 70 | Y12: =+Y84 -> Inventec/ZT Systems | Z12: =+VLOOKUP(Y12,$Y$83:$Z$93,2,FALSE) -> 0.20334671 | AA12: =+VLOOKUP(Y12,$Y$124:$Z$137,2,FALSE) -> 0.089400352
B13: A100 | C13: 93 | D13: =(D2/8)-D19 -> 32.172836 | E13: =(E2/8)-E19 -> 0 | F13: =(F2/8)-F19 -> 0 | G13: =(G2/8)-G19 -> 0 | H13: =(H2/8)-H19 -> 0 | Y13: =+Y85 -> FII/HH | Z13: =+VLOOKUP(Y13,$Y$83:$Z$93,2,FALSE) -> 0.24295971 | AA13: =+VLOOKUP(Y13,$Y$124:$Z$137,2,FALSE) -> 0.16738789
B14: H100/H200/H20 | C14: 6.5 | D14: =(D3/8)-D20 -> 154.15897 | E14: =(E3/8)-E20 -> 467.325 | F14: =(F3/8)-F20 -> 64.1125 | G14: =(G3/8)-G20 -> 0 | H14: =(H3/8)-H20 -> 0 | Y14: =+Y86 -> Wiwynn | Z14: =+VLOOKUP(Y14,$Y$83:$Z$93,2,FALSE) -> 0.0079225992 | AA14: =+VLOOKUP(Y14,$Y$124:$Z$137,2,FALSE) -> 0.0019021351
B15: B200/B300 | C15: 0 | D15: =(D4/8)-D21 -> 0 | E15: =(E4/8)-E21 -> 45.4 | F15: 90 | G15: 30 | H15: 0 | Y15: =+Y87 -> Wistron | Z15: =+VLOOKUP(Y15,$Y$83:$Z$93,2,FALSE) -> 0.015845198 | AA15: =+VLOOKUP(Y15,$Y$124:$Z$137,2,FALSE) -> 0.024727757
B16: R200 | C16: 0 | F16: =+(F5/8) -> 0 | G16: 60 | H16: 20 | Y16: =+Y88 -> Super Micro | Z16: =+VLOOKUP(Y16,$Y$83:$Z$93,2,FALSE) -> 0.13679688 | AA16: =+VLOOKUP(Y16,$Y$124:$Z$137,2,FALSE) -> 0.11098959
B17: R300 | G17: =+(G6/8) -> 6.825 | H17: 50 | Y17: =+Y91 -> Giga-Byte | Z17: =+VLOOKUP(Y17,$Y$83:$Z$93,2,FALSE) -> 0.026408664 | AA17: =+VLOOKUP(Y17,$Y$124:$Z$137,2,FALSE) -> 0.034809073
B18: DGX | C18: =SUM(C19:C20) -> 5 | D18: =SUM(D19:D21) -> 3 | E18: =SUM(E19:E21) -> 13 | F18: =SUM(F19:F21) -> 7 | G18: =SUM(G19:G21) -> 1 | H18: =SUM(H19:H21) -> 0
B19: A100 | C19: 4.3 | D19: 1 | E19: 0 | F19: 0 | G19: 0 | H19: 0 | Y19: =+Y92 -> Inspur | Z19: =+VLOOKUP(Y19,$Y$83:$Z$93,2,FALSE) -> 0.12676159 | AA19: =+VLOOKUP(Y19,$Y$124:$Z$137,2,FALSE) -> 0.097008892
B20: H100 | C20: 0.7 | D20: 2 | E20: 13 | F20: 6 | G20: 0 | H20: 0 | Y20: Asustek | Z20: =+IFERROR(VLOOKUP(Y20,$Y$83:$Z$93,2,FALSE),0) -> 0 | AA20: =+VLOOKUP(Y20,$Y$124:$Z$137,2,FALSE) -> 0.0085596082
B21: B200/B300 | C21: 0 | D21: 0 | E21: 0 | F21: 1 | G21: 1 | H21: 0 | Y21: =+Y93 -> Others | Z21: =+VLOOKUP(Y21,$Y$83:$Z$93,2,FALSE) -> 0.12376052 | AA21: =+VLOOKUP(Y21,$Y$124:$Z$137,2,FALSE) -> 0.24361596
B22: Rack-scale | E22: =+SUM(E23:E25) -> 0 | F22: =+SUM(F23:F25) -> 28.918 | G22: =+SUM(G23:G25) -> 77.375 | H22: =+SUM(H23:H26) -> 99.2945 | T22: Check | U22: +'ODM share analysis'!R[164]C[-3]*1000-'GB200-300 Tracker (2025)'!R[3]C | Y22: Total | Z22: =SUM(Z11:Z21) -> 0.9683096 | AA22: =SUM(AA11:AA21) -> 0.90964858
B23: GB200 NVL72 | F23: =+'GB200-300 Tracker'!BE40/1000 -> 24.218 | G23: =+'GB200-300 Tracker'!BF40/1000 -> 1.1153333 | H23: =+'GB200-300 Tracker'!BG40/1000 -> 0
B24: GB300 NVL72 | F24: =+'GB200-300 Tracker'!BE41/1000 -> 4.7 | G24: =+'GB200-300 Tracker'!BF41/1000 -> 73.259667 | H24: =+'GB200-300 Tracker'!BG41/1000 -> 7.1972778
B25: VR200 NVL72 | F25: =+'GB200-300 Tracker'!BE42/1000 -> 0 | G25: =+'GB200-300 Tracker'!BF42/1000 -> 3 | H25: =+'GB200-300 Tracker'!BG42/1000 -> 89.097222
B26: VR300 NVL576 | F26: =+'GB200-300 Tracker'!BE43/1000 -> 0 | G26: =+'GB200-300 Tracker'!BF43/1000 -> 0 | H26: =+'GB200-300 Tracker'!BG43/1000 -> 3
B27: Others (L40S, etc) | C27: 25 | D27: =+D7/4 -> 66.90595 | E27: =+E7/4 -> 239.5 | F27: =+F7/4 -> 111.625 | G27: =+G7/4 -> 216.05 | H27: =+H7/4 -> 237.625 | Y27: Nvidia HGX/DGX demand
Y28: Mix | Z28: 2023 | AA28: 2024
B29: y/y | Y29: Microsoft | Z29: =+VLOOKUP(Y29,$Y$104:$Z$118,2,FALSE) -> 0.17429718 | AA29: =+VLOOKUP(Y29,$Y$146:$Z$163,2,FALSE) -> 0.13314946
B30: =+B11 -> HGX+DGX (8x GPU) | E30: =+IFERROR(E11/D11-1,"--") -> 1.776739 | F30: =+IFERROR(F11/E11-1,"--") -> -0.69354225 | G30: =+IFERROR(G11/F11-1,"--") -> -0.39281558 | H30: =+IFERROR(H11/G11-1,"--") -> -0.28443649 | Y30: Google | Z30: =+VLOOKUP(Y30,$Y$104:$Z$118,2,FALSE) -> 0.079225992 | AA30: =+VLOOKUP(Y30,$Y$146:$Z$163,2,FALSE) -> 0.057064054
B31: =+B12 -> HGX | D31: =+IFERROR(D12/C12-1,"--") -> -- | E31: =+IFERROR(E12/D12-1,"--") -> 1.7516773 | F31: =+IFERROR(F12/E12-1,"--") -> -0.69942464 | G31: =+IFERROR(G12/F12-1,"--") -> -0.3717252 | H31: =+IFERROR(H12/G12-1,"--") -> -0.27704622 | Y31: Amazon | Z31: =+VLOOKUP(Y31,$Y$104:$Z$118,2,FALSE) -> 0.052817328 | AA31: =+VLOOKUP(Y31,$Y$146:$Z$163,2,FALSE) -> 0.06277046
B32: =+B13 -> A100 | D32: =+IFERROR(D13/C13-1,"--") -> -0.65405553 | E32: NM | F32: =+IFERROR(F13/E13-1,"--") -> -- | G32: =+IFERROR(G13/F13-1,"--") -> -- | H32: =+IFERROR(H13/G13-1,"--") -> -- | Y32: Meta Platforms | Z32: =+VLOOKUP(Y32,$Y$104:$Z$118,2,FALSE) -> 0.10563466 | AA32: =+VLOOKUP(Y32,$Y$146:$Z$163,2,FALSE) -> 0.06657473
B33: =+B14 -> H100/H200/H20 | D33: =+IFERROR(D14/C14-1,"--") -> 22.716764 | E33: =+IFERROR(E14/D14-1,"--") -> 2.0314487 | F33: =+IFERROR(F14/E14-1,"--") -> -0.86280961 | G33: =+IFERROR(G14/F14-1,"--") -> -1 | H33: =+IFERROR(H14/G14-1,"--") -> -- | Y33: Dell | Z33: =+VLOOKUP(Y33,$Y$104:$Z$118,2,FALSE) -> #N/A | AA33: =+VLOOKUP(Y33,$Y$146:$Z$163,2,FALSE) -> 0.060868325
B34: =+B15 -> B200/B300 | D34: =+IFERROR(D15/C15-1,"--") -> -- | E34: =+IFERROR(E15/D15-1,"--") -> -- | F34: =+IFERROR(F15/E15-1,"--") -> 0.98237885 | G34: =+IFERROR(G15/F15-1,"--") -> -0.66666667 | H34: =+IFERROR(H15/G15-1,"--") -> -1 | Y34: Coreweave | Z34: =+VLOOKUP(Y34,$Y$104:$Z$118,2,FALSE) -> 0.07394426 | AA34: =+VLOOKUP(Y34,$Y$146:$Z$163,2,FALSE) -> 0.085596082
B35: =+B16 -> R200 | D35: =+IFERROR(D16/C16-1,"--") -> -- | E35: =+IFERROR(E16/D16-1,"--") -> -- | F35: =+IFERROR(F16/E16-1,"--") -> -- | G35: =+IFERROR(G16/F16-1,"--") -> -- | H35: =+IFERROR(H16/G16-1,"--") -> -0.66666667 | Y35: Oracle | Z35: =+VLOOKUP(Y35,$Y$104:$Z$118,2,FALSE) -> 0.079225992 | AA35: =+VLOOKUP(Y35,$Y$146:$Z$163,2,FALSE) -> 0.038042703
B36: =+B18 -> DGX | D36: =+IFERROR(D18/C18-1,"--") -> -0.4 | E36: =+IFERROR(E18/D18-1,"--") -> 3.3333333 | F36: =+IFERROR(F18/E18-1,"--") -> -0.46153846 | G36: =+IFERROR(G18/F18-1,"--") -> -0.85714286 | H36: =+IFERROR(H18/G18-1,"--") -> -1 | Y36: BBAT | Z36: =+SUM(Z111:Z114) -> 0.11091639 | AA36: =+SUM(Z156:Z159) -> 0.20923487
B37: =+B19 -> A100 | D37: =+IFERROR(D19/C19-1,"--") -> -0.76744186 | E37: NM | F37: =+IFERROR(F19/E19-1,"--") -> -- | G37: =+IFERROR(G19/F19-1,"--") -> -- | H37: =+IFERROR(H19/G19-1,"--") -> -- | Y37: Others | Z37: =+VLOOKUP(Y37,$Y$104:$Z$118,2,FALSE)+Z110 -> 0.30967752 | AA37: =+VLOOKUP(Y37,$Y$146:$Z$163,2,FALSE)+Z155 -> 0.21089923
B38: =+B20 -> H100 | D38: =+IFERROR(D20/C20-1,"--") -> 1.8571429 | E38: =+IFERROR(E20/D20-1,"--") -> 5.5 | F38: =+IFERROR(F20/E20-1,"--") -> -0.53846154 | G38: =+IFERROR(G20/F20-1,"--") -> -1 | H38: =+IFERROR(H20/G20-1,"--") -> -- | Y38: Total | Z38: =SUM(Z29:Z37) -> #N/A | AA38: =SUM(AA29:AA37) -> 0.92419991
B39: =+B21 -> B200/B300 | D39: =+IFERROR(D21/C21-1,"--") -> -- | E39: =+IFERROR(E21/D21-1,"--") -> -- | F39: =+IFERROR(F21/E21-1,"--") -> -- | G39: =+IFERROR(G21/F21-1,"--") -> 0 | H39: =+IFERROR(H21/G21-1,"--") -> -1
B40: =+B22 -> Rack-scale | D40: =+IFERROR(D22/C22-1,"--") -> -- | E40: =+IFERROR(E22/D22-1,"--") -> -- | F40: =+IFERROR(F22/E22-1,"--") -> -- | G40: =+IFERROR(G22/F22-1,"--") -> 1.6756691 | H40: =+IFERROR(H22/G22-1,"--") -> 0.28328918
B41: =+B23 -> GB200 NVL72 | D41: =+IFERROR(D23/C23-1,"--") -> -- | E41: =+IFERROR(E23/D23-1,"--") -> -- | F41: =+IFERROR(F23/E23-1,"--") -> -- | G41: =+IFERROR(G23/F23-1,"--") -> -0.9539461 | H41: =+IFERROR(H23/G23-1,"--") -> -1
B42: =+B24 -> GB300 NVL72 | D42: =+IFERROR(D24/C24-1,"--") -> -- | E42: =+IFERROR(E24/D24-1,"--") -> -- | F42: =+IFERROR(F24/E24-1,"--") -> -- | G42: =+IFERROR(G24/F24-1,"--") -> 14.587163 | H42: =+IFERROR(H24/G24-1,"--") -> -0.90175661
B43: =+B25 -> VR200 NVL72 | D43: =+IFERROR(D25/C25-1,"--") -> -- | E43: =+IFERROR(E25/D25-1,"--") -> -- | F43: =+IFERROR(F25/E25-1,"--") -> -- | G43: =+IFERROR(G25/F25-1,"--") -> -- | H43: =+IFERROR(H25/G25-1,"--") -> 28.699074
B44: =+B26 -> VR300 NVL576 | D44: =+IFERROR(D26/C26-1,"--") -> -- | E44: =+IFERROR(E26/D26-1,"--") -> -- | F44: =+IFERROR(F26/E26-1,"--") -> -- | G44: =+IFERROR(G26/F26-1,"--") -> -- | H44: =+IFERROR(H26/G26-1,"--") -> --
B45: =+B27 -> Others (L40S, etc) | E45: =+IFERROR(E27/D27-1,"--") -> 2.5796517 | F45: =+IFERROR(F27/E27-1,"--") -> -0.53392484 | G45: =+IFERROR(G27/F27-1,"--") -> 0.93549832 | H45: =+IFERROR(H27/G27-1,"--") -> 0.099861143
B47: GPU # (exclude PCIe) | C47: =+C11*8 -> 836 | D47: =SUM(D2:D6) -> 1514.6544 | E47: =SUM(E2:E6) -> 4205.8 | F47: =SUM(F2:F6) -> 4840.7 | G47: =SUM(G2:G6) -> 5814.9 | H47: =SUM(H2:H6) -> 5430.2
B48: y/y | D48: =+D47/C47-1 -> 0.81178759 | E48: =+E47/D47-1 -> 1.776739 | F48: =+F47/E47-1 -> 0.1509582 | G48: =+G47/F47-1 -> 0.20125189 | H48: =+H47/G47-1 -> -0.06615763
B49: DC GPU ($bn) | C49: 10.618592 | D49: 38.01302 | E49: 100.68721 | F49: 153.83546 | G49: 212.97575 | H49: 248.19468
B50: y/y | D50: =+D49/C49-1 -> 2.579855 | E50: =+E49/D49-1 -> 1.6487557 | F50: =+F49/E49-1 -> 0.52785505 | G50: =+G49/F49-1 -> 0.38443863 | H50: =+H49/G49-1 -> 0.16536593
B53: ODM share
B54: Quanta
B55: Inventec
B56: Wiwynn
B57: FII/HH
B58: Others
B60: Total server | C60: 14960.348 | D60: 12357.341 | E60: 13892.002 | F60: 14220.705 | G60: 14660.639 | H60: 15029.699
B61: Nvidia AI server mix | C61: =+#REF!/C60 -> #REF! | D61: =+#REF!/D60 -> #REF! | E61: =+#REF!/E60 -> #REF! | F61: =+#REF!/F60 -> #REF! | G61: =+#REF!/G60 -> #REF! | H61: =+#REF!/H60 -> #REF!
F63: Demand | G63: TSMC
B64: Blackwell units | F64: =+F65+F66 -> 2810.096 | G64: 5500
B65: GB200/GB300 | F65: =+D170*72 -> 2082.096 | G65: =+F65 -> 2082.096
B66: B200/B300 HGX | F66: =+(F15+F21)*8 -> 728 | G66: =+G64-G65 -> 3417.904
B68: Blackwell mix
B69: GB200/GB300 | F69: =+F65/F64 -> 0.74093412 | G69: =+G65/G64 -> 0.37856291
B70: B200/B300 HGX | F70: =+F66/F64 -> 0.25906588 | G70: =+G66/G64 -> 0.62143709
B72: Last update: February 4, 2025
D74: =+D10 -> 2023 | E74: =+E10 -> 2024 | F74: =+F10 -> 2025 | G74: =+G10 -> 2026 | H74: =+H10 -> 2027
B75: Implied Capex (US$ bn) | C75: =+SUM(C77:C85)+C92 -> 0 | D75: =+((D13+D19)*D78+(D14+D20)*D79+(D15+D21)*D80+D16*D81+D23*D83+D25*D82+D27*D84)/1000 -> 47.869763 | E75: =+((E13+E19)*E78+(E14+E20)*E79+(E15+E21)*E80+E16*E81+E23*E83+E25*E82+E27*E84)/1000 -> 150.46625 | F75: =+((F13+F19)*F78+(F14+F20)*F79+(F15+F21)*F80+F16*F81+F23*F83+F25*F82+F27*F84)/1000 -> 132.56127 | G75: =+((G13+G19)*G78+(G14+G20)*G79+(G15+G21)*G80+G16*G81+G23*G83+G25*G82+G27*G84)/1000 -> 56.3041 | H75: =+((H13+H19)*H78+(H14+H20)*H79+(H15+H21)*H80+H16*H81+H23*H83+H25*H82+H27*H84)/1000 -> 184.60875
B77: ASP (US$ k)
B78: A100 | D78: 125 | E78: 125 | F78: 125 | G78: 125 | H78: 125
B79: H100 | D79: 250 | E79: 250 | F79: 250 | G79: 250 | H79: 250
B80: B100 | D80: 300 | E80: 300 | F80: 300 | G80: 300 | H80: 300
B81: R100 | D81: 380 | E81: 380 | F81: 380 | G81: 380 | H81: 380
B82: GB200 (NVL36) | D82: 1800 | E82: 1800 | F82: 1800 | G82: 1800 | H82: 1800 | Y82: ODM share
B83: GB200 (NVL72) | D83: 3300 | E83: 3300 | F83: 3300 | G83: 3300 | H83: 3300 | Y83: =+I85 -> Quanta | Z83: =+V85/V$96 -> 0.084507725
B84: L40S/H20, etc | D84: 70 | E84: 70 | F84: 70 | G84: 70 | H84: 70 | I84: ODM/OEM share | J84: MSFT | K84: GOOG | L84: AWS | M84: Meta | N84: BBAT | O84: CW | P84: Tesla/X | Q84: Oracle | R84: Apple | S84: AD | T84: Taiga | U84: Others | V84: Total | Y84: =+I86 -> Inventec/ZT Systems | Z84: =+V86/V$96 -> 0.20334671
I85: Quanta | J85: 5 | K85: 2.5 | L85: 2.5 | M85: 6 | N85: 0 | P85: 0 | U85: 0 | V85: =+SUM(J85:U85) -> 16 | Y85: =+I87 -> FII/HH | Z85: =+V87/V$96 -> 0.24295971
B86: 2023 ODM share analysis (8x GPU HGX+DGX) | I86: Inventec/ZT Systems | J86: 17 | K86: 6.5 | N86: 9 | U86: 6 | V86: =+SUM(J86:U86) -> 38.5 | Y86: =+I88 -> Wiwynn | Z86: =+V88/V$96 -> 0.0079225992
B87: 2023 AI server volume | D87: =+D13+D14+D18 -> 189.3318 | I87: FII/HH | J87: 9 | K87: 6 | L87: 7 | N87: 1 | Q87: 15 | U87: 8 | V87: =+SUM(J87:U87) -> 46 | Y87: =+I89 -> Wistron | Z87: =+V89/V$96 -> 0.015845198
B88: Microsoft | D88: 33 | I88: Wiwynn | J88: 0.5 | L88: 0 | M88: 0 | U88: 1 | V88: =+SUM(J88:U88) -> 1.5 | Y88: =+I90 -> Super Micro | Z88: =+V90/V$96 -> 0.13679688
B89: Google | D89: 15 | I89: Wistron | U89: =+D18 -> 3 | V89: =+SUM(J89:U89) -> 3 | Y89: =+I91 -> Dell | Z89: =+V91/V$96 -> 0.026408664
B90: Amazon | D90: 10 | I90: Super Micro | M90: 11 | O90: 8 | P90: 5 | Q90: 0 | S90: 0.9 | U90: 1 | V90: =+SUM(J90:U90) -> 25.9 | Y90: =+I92 -> HPE | Z90: =+V92/V$96 -> 0.0052817328
B91: Meta Platforms | D91: 20 | I91: Dell | O91: 2 | U91: 3 | V91: =+SUM(J91:U91) -> 5 | Y91: =+I93 -> Giga-Byte | Z91: =+V93/V$96 -> 0.026408664
B92: Other non-hyperscalers | D92: =+D87-SUM(D88:D91) -> 111.3318 | I92: HPE | U92: 1 | V92: =+SUM(J92:U92) -> 1 | Y92: =+I94 -> Inspur | Z92: =+V94/V$96 -> 0.12676159
B93: Coreweave | D93: 14 | I93: Giga-Byte | O93: 4 | T93: =+D103 -> 0.3 | U93: 0.7 | V93: =+SUM(J93:U93) -> 5 | Y93: =+I95 -> Others | Z93: =+V95/V$96 -> 0.12376052
B94: Baidu | D94: 3 | I94: Inspur | N94: 10 | U94: 14 | V94: =+SUM(J94:U94) -> 24
B95: Alibaba | D95: 3 | I95: Others | J95: =+J96-SUM(J85:J94) -> 1.5 | K95: =+K96-SUM(K85:K94) -> 0 | L95: =+L96-SUM(L85:L94) -> 0.5 | M95: =+M96-SUM(M85:M94) -> 3 | N95: =+N96-SUM(N85:N94) -> 1 | O95: =+O96-SUM(O85:O94) -> 0 | P95: =+P96-SUM(P85:P94) -> 1 | Q95: =+Q96-SUM(Q85:Q94) -> 0 | R95: 0 | S95: =+S96-SUM(S85:S94) -> 0 | T95: =+T96-SUM(T85:T94) -> 0 | U95: =+U96-SUM(U85:U94) -> 16.431803 | V95: =+SUM(J95:U95) -> 23.431803
B96: Tencent | D96: 5 | I96: Total | J96: =+D88 -> 33 | K96: =+D89 -> 15 | L96: =+D90 -> 10 | M96: =+D91 -> 20 | N96: =+SUM(D94:D97) -> 21 | O96: =+D93 -> 14 | P96: =+D99+D98 -> 6 | Q96: =+D100 -> 15 | R96: 0 | S96: =+D102 -> 0.9 | T96: =+D103 -> 0.3 | U96: =+D92-SUM(N96:T96) -> 54.131803 | V96: =+SUM(J96:U96) -> 189.3318
B97: ByteDance | D97: 10
B98: X | D98: 1
B99: Tesla | D99: 5
B100: Oracle | D100: 15
B101: Lambda | D101: 1.5
B102: Applied Digital | D102: 0.9
B103: Taiga Cloud | D103: 0.3 | Y103: Mix
B104: Others | D104: =+D92-SUM(D93:D103) -> 52.631803 | Y104: =+B107 -> Microsoft | Z104: =+VLOOKUP(Y104,$B$107:$D$122,3,FALSE) -> 0.17429718
Y105: =+B108 -> Google | Z105: =+VLOOKUP(Y105,$B$107:$D$122,3,FALSE) -> 0.079225992
B106: Mix | Y106: =+B109 -> Amazon | Z106: =+VLOOKUP(Y106,$B$107:$D$122,3,FALSE) -> 0.052817328
B107: =+B88 -> Microsoft | D107: =+D88/D$87 -> 0.17429718 | Y107: =+B110 -> Meta Platforms | Z107: =+VLOOKUP(Y107,$B$107:$D$122,3,FALSE) -> 0.10563466
B108: =+B89 -> Google | D108: =+D89/D$87 -> 0.079225992 | Y108: =+B111 -> Coreweave | Z108: =+VLOOKUP(Y108,$B$107:$D$122,3,FALSE) -> 0.07394426
B109: =+B90 -> Amazon | D109: =+D90/D$87 -> 0.052817328 | Y109: =+B118 -> Oracle | Z109: =+VLOOKUP(Y109,$B$107:$D$122,3,FALSE) -> 0.079225992
B110: =+B91 -> Meta Platforms | D110: =+D91/D$87 -> 0.10563466 | Y110: Tesla/X | Z110: =+D116+D117 -> 0.031690397
...

Sheet GB200-300 Tracker
B2: k units | C2: 2024 | D2: 2025 | E2: 2026 | F2: 2027
B3: B200 chips | C3: 400 | D3: =2240 -> 2240 | E3: 0 | F3: 0
B4: B300 chips | D4: =2834 -> 2834 | E4: 5460 | F4: 0
B5: R200 chips | E5: 2080 | F5: =+E4 -> 5460
B6: R300 chips | F6: =+E5 -> 2080
B8: B200 Analysis | D8: =+D2 -> 2025
B9: Total B200 chips | D9: =+D3+C3 -> 2640
B10: B200 HGX assumptions | D10: =90*8 -> 720
B11: B200 chips left for GB200 | D11: =+D9-D10 -> 1920
B12: Maximum GB200 NVL72 rack output | D12: =+D11/72 -> 26.666667
B13: GB200 NVL72 rack yield | D13: 0.95
B14: GB200 NVL72 racks (accounting for yield) | D14: =+D12*D13 -> 25.333333
B16: B300 Analysis | D16: =+D2 -> 2025 | E16: =+E2 -> 2026
B17: Total B300 chips | D17: =+D4 -> 2834 | E17: =+E4 -> 5460
B18: B300 HGX assumptions | D18: =30*8 -> 240 | E18: =200*8 -> 1600
B19: B300 chips left for GB300 | D19: =+D17-D18 -> 2594 | E19: =+E17-E18 -> 3860
B20: Maximum GB300 NVL72 rack output | D20: =+D19/72 -> 36.027778 | E20: =+E19/72 -> 53.611111
B21: GB300 NVL72 rack yield | D21: 0.95 | E21: 0.95
B22: GB300 NVL72 racks (accounting for yield) | D22: =+D20*D21 -> 34.226389 | E22: =+E20*E21 -> 50.930556
B23: GB300 NVL72 racks shipped in CY25 | D23: =+AU41/1000 -> 4.7
B24: GB300 NVL72 racks rolled into CY26 | D24: =+D22-D23 -> 29.526389
B25: Total GB300 NVL72 racks in CY26 | E25: =+D24+E22 -> 80.456944
B27: R200 Analysis | E27: =+E2 -> 2026 | F27: =+F2 -> 2027
B28: Total R200 chips | E28: =+E5 -> 2080 | F28: =+F5 -> 5460
B29: R200 HGX assumptions | E29: =20*8 -> 160 | F29: =50*8 -> 400
B30: R200 chips left for VR200 | E30: =+E28-E29 -> 1920 | F30: =+F28-F29 -> 5060
B31: Maximum VR200 NVL72 rack output | E31: =+E30/72 -> 26.666667 | F31: =+F30/72 -> 70.277778
B32: VR200 NVL72 rack yield | E32: 0.95 | F32: 0.95
B33: VR200 NVL72 racks (accounting for yield) | E33: =+E31*E32 -> 25.333333 | F33: =+F31*F32 -> 66.763889
B34: VR200 NVL72 racks shipped in CY26 | E34: =+AY42/1000 -> 3
B35: VR200 NVL72 racks rolled into CY27 | E35: =+E33-E34 -> 22.333333 | M35: Check | N35: =+'ODM share analysis'!V186*1000-'GB200-300 Tracker'!AG40 -> 0 | Y35: Check | Z35: =+'ODM share analysis'!V213*1000-AN40 -> 0
B36: Total VR200 NVL72 racks in CY27 | F36: =+E35+F33 -> 89.097222
C38: 2025 | O38: 2026
B39: Racks | C39: Jan | D39: Feb | E39: Mar | F39: Apr | G39: May | H39: Jun | I39: Jul | J39: Aug | K39: Sep | L39: Oct | M39: Nov | N39: Dec | O39: Jan | P39: Feb | Q39: Mar | R39: Apr | S39: May-E | T39: Jun-E | U39: Jul-E | V39: Aug-E | W39: Sep-E | X39: Oct-E | Y39: Nov-E | Z39: Dec-E | AB39: Racks | AC39: 1Q | AD39: 2Q | AE39: 3Q | AF39: 4Q | AG39: 2025 | AI39: Racks | AJ39: 1Q | AK39: 2Q | AL39: 3Q | AM39: 4Q | AN39: 2026 | AQ39: Racks | AR39: 1Q25 | AS39: 2Q25 | AT39: 3Q25 | AU39: 4Q25 | AV39: 1Q26 | AW39: 2Q26 | AX39: 3Q26 | AY39: 4Q26 | AZ39: 1Q27 | BA39: 2Q27 | BB39: 3Q27 | BC39: 4Q27 | BE39: 2025 | BF39: 2026 | BG39: 2027
B40: GB racks (NVL72) | C40: =+SUM(C42:C46) -> 127 | D40: =+SUM(D42:D46) -> 283 | E40: =+SUM(E42:E46) -> 498 | F40: =+SUM(F42:F46) -> 692 | G40: =+SUM(G42:G46) -> 1759 | H40: =+SUM(H42:H46) -> 1845 | I40: =+SUM(I42:I46) -> 1740 | J40: =+SUM(J42:J46) -> 2359 | ... Z40: =+SUM(Z42:Z46) -> 4475 | AB40: GB racks (NVL72) | AC40: =+SUM(AC42:AC46) -> 908 | AD40: =+SUM(AD42:AD46) -> 4296 | AE40: =+SUM(AE42:AE46) -> 8264 | AF40: =+SUM(AF42:AF46) -> 15450 | AG40: =+SUM(AG42:AG46) -> 28918 | AI40: GB racks (NVL72) | AJ40: =+SUM(AJ42:AJ46) -> 20775 | AK40: =+SUM(AK42:AK46) -> 24925 | AL40: =+SUM(AL42:AL46) -> 18400 | AM40: =+SUM(AM42:AM46) -> 13275 | AN40: =+SUM(AN42:AN46) -> 77375 | AQ40: GB200 | AR40: =+AC40 -> 908 | AS40: =+AD40 -> 4296 | AT40: =+AE40 -> 8264 | AU40: 10750 | AV40: =+D14*1000-SUM(AR40:AU40) -> 1115.3333 | AW40: 0 | AX40: 0 | AY40: 0 | AZ40: 0 | BA40: 0 | BB40: 0 | BC40: 0 | BE40: =+SUM(AR40:AU40) -> 24218 | BF40: =+SUM(AV40:AY40) -> 1115.3333 | BG40: =+SUM(AZ40:BC40) -> 0
AQ41: GB300 | AR41: 0 | AS41: 0 | AT41: 0 | AU41: =+AG40-SUM(AR41:AT41)-SUM(AR40:AU40) -> 4700 | AV41: =+AJ40-AV40 -> 19659.667 | AW41: =+AK40-AW40 -> 24925 | AX41: =+AL40-AX40 -> 18400 | AY41: =+AM40-AY42 -> 10275 | AZ41: =+E25*1000-SUM(AV41:AY41) -> 7197.2778 | BA41: 0 | BB41: 0 | BC41: 0 | BE41: =+SUM(AR41:AU41) -> 4700 | BF41: =+SUM(AV41:AY41) -> 73259.667 | BG41: =+SUM(AZ41:BC41) -> 7197.2778
B42: Hon Hai | C42: 30 | D42: 150 | E42: 320 | F42: 400 | G42: 500 | H42: 700 | I42: 700 | J42: 1500 | K42: 2600 | L42: 2500 | M42: 2500 | N42: 2800 | O42: 2400 | P42: 2400 | Q42: 3700 | R42: 3700 | S42: 3200 | T42: 3100 | U42: 3000 | V42: 2500 | W42: 2000 | X42: 1700 | Y42: 2000 | Z42: 2000 | AB42: Hon Hai | AC42: =SUM(C42:E42) -> 500 | AD42: =SUM(F42:H42) -> 1600 | AE42: =SUM(I42:K42) -> 4800 | AF42: =SUM(L42:N42) -> 7800 | AG42: =+SUM(AC42:AF42) -> 14700 | AH42: =+AG42/$AG$40 -> 0.50833391 | AI42: Hon Hai | AJ42: =SUM(O42:Q42) -> 8500 | AK42: =SUM(R42:T42) -> 10000 | AL42: =SUM(U42:W42) -> 7500 | AM42: =SUM(X42:Z42) -> 5700 | AN42: =+SUM(AJ42:AM42) -> 31700 | AO42: =+AN42/$AN$40 -> 0.40969305 | AQ42: VR200 | AR42: 0 | AS42: 0 | AT42: 0 | AU42: 0 | AV42: 0 | AW42: 0 | AX42: 0 | AY42: 3000 | AZ42: 12500 | BA42: 23500 | BB42: 27500 | BC42: =+F36*1000-SUM(AZ42:BB42) -> 25597.222 | BE42: =+SUM(AR42:AU42) -> 0 | BF42: =+SUM(AV42:AY42) -> 3000 | BG42: =+SUM(AZ42:BC42) -> 89097.222
B43: Quanta | C43: 50 | D43: 50 | E43: 100 | F43: 125 | G43: 300 | H43: 375 | I43: 420 | J43: 459 | K43: 675 | L43: 870 | M43: 1050 | N43: 1650 | O43: 1425 | P43: 1350 | Q43: 2150 | R43: 2100 | S43: 2500 | T43: 2700 | U43: 1900 | V43: 1800 | W43: 1200 | X43: 600 | Y43: 500 | Z43: 475 | AB43: Quanta | AC43: =SUM(C43:E43) -> 200 | AD43: =SUM(F43:H43) -> 800 | AE43: =SUM(I43:K43) -> 1554 | AF43: =SUM(L43:N43) -> 3570 | AG43: =+SUM(AC43:AF43) -> 6124 | AH43: =+AG43/$AG$40 -> 0.21177122 | AI43: Quanta | AJ43: =SUM(O43:Q43) -> 4925 | AK43: =SUM(R43:T43) -> 7300 | AL43: =SUM(U43:W43) -> 4900 | AM43: =SUM(X43:Z43) -> 1575 | AN43: =+SUM(AJ43:AM43) -> 18700 | AO43: =+AN43/$AN$40 -> 0.24168013 | AQ43: VR300 | AR43: 0 | AS43: 0 | AT43: 0 | AU43: 0 | AV43: 0 | AW43: 0 | AX43: 0 | AY43: 0 | AZ43: 0 | BA43: 0 | BB43: 0 | BC43: 3000 | BE43: =+SUM(AR43:AU43) -> 0 | BF43: =+SUM(AV43:AY43) -> 0 | BG43: =+SUM(AZ43:BC43) -> 3000
B44: Wistron | C44: 45 | D44: 80 | E44: 75 | F44: 160 | G44: 950 | H44: 750 | I44: 500 | J44: 150 | K44: 590 | L44: 325 | M44: 1250 | N44: 850 | O44: 950 | P44: 1450 | Q44: 1550 | R44: 1325 | S44: 1400 | T44: 1450 | U44: 1200 | V44: 1000 | W44: 800 | X44: 1000 | Y44: 1000 | Z44: 1000 | AB44: Wistron | AC44: =SUM(C44:E44) -> 200 | AD44: =SUM(F44:H44) -> 1860 | AE44: =SUM(I44:K44) -> 1240 | AF44: =SUM(L44:N44) -> 2425 | AG44: =+SUM(AC44:AF44) -> 5725 | AH44: =+AG44/$AG$40 -> 0.19797358 | AI44: Wistron | AJ44: =SUM(O44:Q44) -> 3950 | AK44: =SUM(R44:T44) -> 4175 | AL44: =SUM(U44:W44) -> 3000 | AM44: =SUM(X44:Z44) -> 3000 | AN44: =+SUM(AJ44:AM44) -> 14125 | AO44: =+AN44/$AN$40 -> 0.1825525 | AQ44: Total | AR44: =SUM(AR40:AR43) -> 908 | AS44: =SUM(AS40:AS43) -> 4296 | AT44: =SUM(AT40:AT43) -> 8264 | AU44: =SUM(AU40:AU43) -> 15450 | AV44: =SUM(AV40:AV43) -> 20775 | AW44: =SUM(AW40:AW43) -> 24925 | AX44: =SUM(AX40:AX43) -> 18400 | AY44: =SUM(AY40:AY43) -> 13275 | ... BC44: =SUM(BC40:BC43) -> 28597.222 | BE44: =+SUM(AR44:AU44) -> 28918 | BF44: =+SUM(AV44:AY44) -> 77375 | BG44: =+SUM(AZ44:BC44) -> 99294.5
B45: Wiwynn | C45: 1 | D45: 2 | E45: 2 | F45: 5 | G45: 5 | H45: 10 | I45: 20 | J45: 50 | K45: 50 | L45: 130 | M45: 140 | N45: 160 | O45: 20 | P45: 30 | Q45: 0 | R45: 0 | S45: 0 | T45: 0 | U45: 0 | V45: 0 | W45: 0 | X45: 0 | Y45: 0 | Z45: 0 | AB45: Wiwynn | AC45: =SUM(C45:E45) -> 5 | AD45: =SUM(F45:H45) -> 20 | AE45: =SUM(I45:K45) -> 120 | AF45: =SUM(L45:N45) -> 430 | AG45: =+SUM(AC45:AF45) -> 575 | AH45: =+AG45/$AG$40 -> 0.019883809 | AI45: Wiwynn | AJ45: =SUM(O45:Q45) -> 50 | AK45: =SUM(R45:T45) -> 0 | AL45: =SUM(U45:W45) -> 0 | AM45: =SUM(X45:Z45) -> 0 | AN45: =+SUM(AJ45:AM45) -> 50 | AO45: =+AN45/$AN$40 -> 0.00064620355
B46: Others | C46: 1 | D46: 1 | E46: 1 | F46: 2 | G46: 4 | H46: 10 | I46: 100 | J46: 200 | K46: 250 | L46: 350 | M46: 450 | N46: 425 | O46: 1150 | P46: 1100 | Q46: 1100 | R46: 1150 | S46: 1150 | T46: 1150 | U46: 1000 | V46: 1000 | W46: 1000 | X46: 1000 | Y46: 1000 | Z46: 1000 | AB46: Others | AC46: =SUM(C46:E46) -> 3 | AD46: =SUM(F46:H46) -> 16 | AE46: =SUM(I46:K46) -> 550 | AF46: =SUM(L46:N46) -> 1225 | AG46: =+SUM(AC46:AF46) -> 1794 | AH46: =+AG46/$AG$40 -> 0.062037485 | AI46: Others | AJ46: =SUM(O46:Q46) -> 3350 | AK46: =SUM(R46:T46) -> 3450 | AL46: =SUM(U46:W46) -> 3000 | AM46: =SUM(X46:Z46) -> 3000 | AN46: =+SUM(AJ46:AM46) -> 12800 | AO46: =+AN46/$AN$40 -> 0.16542811 | AQ46: Mix
AQ47: =+AQ40 -> GB200 | AR47: =+AR40/AR$44 -> 1 | AS47: =+AS40/AS$44 -> 1 | AT47: =+AT40/AT$44 -> 1 | AU47: =+AU40/AU$44 -> 0.69579288 | AV47: =+AV40/AV$44 -> 0.053686322 | AW47: =+AW40/AW$44 -> 0 | AX47: =+AX40/AX$44 -> 0 | AY47: =+AY40/AY$44 -> 0 | ... BC47: =+BC40/BC$44 -> 0 | BE47: =+BE40/BE$44 -> 0.83747147 | BF47: =+BF40/BF$44 -> 0.014414647 | BG47: =+BG40/BG$44 -> 0
B48: Chart label | C48: =+C40/1000 -> 0.127 | D48: =+D40/1000 -> 0.283 | E48: =+E40/1000 -> 0.498 | F48: =+F40/1000 -> 0.692 | G48: =+G40/1000 -> 1.759 | H48: =+H40/1000 -> 1.845 | I48: =+I40/1000 -> 1.74 | J48: =+J40/1000 -> 2.359 | ... Z48: =+Z40/1000 -> 4.475 | AB48: Chart label | AC48: =+AC40/1000 -> 0.908 | AD48: =+AD40/1000 -> 4.296 | AE48: =+AE40/1000 -> 8.264 | AF48: =+AF40/1000 -> 15.45 | AG48: =+AG40/1000 -> 28.918 | AI48: Chart label | AJ48: =+AJ40/1000 -> 20.775 | AK48: =+AK40/1000 -> 24.925 | AL48: =+AL40/1000 -> 18.4 | AM48: =+AM40/1000 -> 13.275 | AN48: =+AN40/1000 -> 77.375 | AQ48: =+AQ41 -> GB300 | AR48: =+AR41/AR$44 -> 0 | AS48: =+AS41/AS$44 -> 0 | AT48: =+AT41/AT$44 -> 0 | AU48: =+AU41/AU$44 -> 0.30420712 | AV48: =+AV41/AV$44 -> 0.94631368 | AW48: =+AW41/AW$44 -> 1 | AX48: =+AX41/AX$44 -> 1 | AY48: =+AY41/AY$44 -> 0.7740113 | ... BC48: =+BC41/BC$44 -> 0 | BE48: =+BE41/BE$44 -> 0.16252853 | BF48: =+BF41/BF$44 -> 0.94681314 | BG48: =+BG41/BG$44 -> 0.072484153
AQ49: =+AQ42 -> VR200 | AR49: =+AR42/AR$44 -> 0 | AS49: =+AS42/AS$44 -> 0 | AT49: =+AT42/AT$44 -> 0 | AU49: =+AU42/AU$44 -> 0 | AV49: =+AV42/AV$44 -> 0 | AW49: =+AW42/AW$44 -> 0 | AX49: =+AX42/AX$44 -> 0 | AY49: =+AY42/AY$44 -> 0.2259887 | ... BC49: =+BC42/BC$44 -> 0.89509471 | BE49: =+BE42/BE$44 -> 0 | BF49: =+BF42/BF$44 -> 0.038772213 | BG49: =+BG42/BG$44 -> 0.89730269
B50: Mix | AB50: Mix | AI50: Mix | AQ50: =+AQ43 -> VR300 | AR50: =+AR43/AR$44 -> 0 | AS50: =+AS43/AS$44 -> 0 | AT50: =+AT43/AT$44 -> 0 | AU50: =+AU43/AU$44 -> 0 | AV50: =+AV43/AV$44 -> 0 | AW50: =+AW43/AW$44 -> 0 | AX50: =+AX43/AX$44 -> 0 | AY50: =+AY43/AY$44 -> 0 | ... BC50: =+BC43/BC$44 -> 0.10490529 | BE50: =+BE43/BE$44 -> 0 | BF50: =+BF43/BF$44 -> 0 | BG50: =+BG43/BG$44 -> 0.030213154
B51: Hon Hai | C51: =+C42/C$40 -> 0.23622047 | D51: =+D42/D$40 -> 0.53003534 | E51: =+E42/E$40 -> 0.64257028 | F51: =+F42/F$40 -> 0.57803468 | G51: =+G42/G$40 -> 0.28425242 | H51: =+H42/H$40 -> 0.37940379 | I51: =+I42/I$40 -> 0.40229885 | J51: =+J42/J$40 -> 0.63586265 | ... Z51: =+Z42/Z$40 -> 0.44692737 | AB51: Hon Hai | AC51: =+AC42/AC$40 -> 0.55066079 | AD51: =+AD42/AD$40 -> 0.37243948 | AE51: =+AE42/AE$40 -> 0.58083253 | AF51: =+AF42/AF$40 -> 0.50485437 | AI51: Hon Hai | AJ51: =+AJ42/AJ$40 -> 0.40914561 | AK51: =+AK42/AK$40 -> 0.40120361 | AL51: =+AL42/AL$40 -> 0.4076087 | AM51: =+AM42/AM$40 -> 0.42937853
B52: Quanta | C52: =+C43/C$40 -> 0.39370079 | D52: =+D43/D$40 -> 0.17667845 | E52: =+E43/E$40 -> 0.20080321 | F52: =+F43/F$40 -> 0.18063584 | G52: =+G43/G$40 -> 0.17055145 | H52: =+H43/H$40 -> 0.20325203 | I52: =+I43/I$40 -> 0.24137931 | J52: =+J43/J$40 -> 0.19457397 | ... Z52: =+Z43/Z$40 -> 0.10614525 | AB52: Quanta | AC52: =+AC43/AC$40 -> 0.22026432 | AD52: =+AD43/AD$40 -> 0.18621974 | AE52: =+AE43/AE$40 -> 0.18804453 | AF52: =+AF43/AF$40 -> 0.23106796 | AI52: Quanta | AJ52: =+AJ43/AJ$40 -> 0.23706378 | AK52: =+AK43/AK$40 -> 0.29287864 | AL52: =+AL43/AL$40 -> 0.26630435 | AM52: =+AM43/AM$40 -> 0.11864407
B53: Wistron | C53: =+C44/C$40 -> 0.35433071 | D53: =+D44/D$40 -> 0.28268551 | E53: =+E44/E$40 -> 0.15060241 | F53: =+F44/F$40 -> 0.23121387 | G53: =+G44/G$40 -> 0.54007959 | H53: =+H44/H$40 -> 0.40650407 | I53: =+I44/I$40 -> 0.28735632 | J53: =+J44/J$40 -> 0.063586265 | ... Z53: =+Z44/Z$40 -> 0.22346369 | AB53: Wistron | AC53: =+AC44/AC$40 -> 0.22026432 | AD53: =+AD44/AD$40 -> 0.43296089 | AE53: =+AE44/AE$40 -> 0.1500484 | AF53: =+AF44/AF$40 -> 0.15695793 | AI53: Wistron | AJ53: =+AJ44/AJ$40 -> 0.19013237 | AK53: =+AK44/AK$40 -> 0.16750251 | AL53: =+AL44/AL$40 -> 0.16304348 | AM53: =+AM44/AM$40 -> 0.2259887
B54: Wiwynn | C54: =+C45/C$40 -> 0.0078740157 | D54: =+D45/D$40 -> 0.0070671378 | E54: =+E45/E$40 -> 0.0040160643 | F54: =+F45/F$40 -> 0.0072254335 | G54: =+G45/G$40 -> 0.0028425242 | H54: =+H45/H$40 -> 0.0054200542 | I54: =+I45/I$40 -> 0.011494253 | J54: =+J45/J$40 -> 0.021195422 | ... Z54: =+Z45/Z$40 -> 0 | AB54: Wiwynn | AC54: =+AC45/AC$40 -> 0.0055066079 | AD54: =+AD45/AD$40 -> 0.0046554935 | AE54: =+AE45/AE$40 -> 0.014520813 | AF54: =+AF45/AF$40 -> 0.027831715 | AI54: Wiwynn | AJ54: =+AJ45/AJ$40 -> 0.0024067389 | AK54: =+AK45/AK$40 -> 0 | AL54: =+AL45/AL$40 -> 0 | AM54: =+AM45/AM$40 -> 0
B55: Others | C55: =+C46/C$40 -> 0.0078740157 | D55: =+D46/D$40 -> 0.0035335689 | E55: =+E46/E$40 -> 0.0020080321 | F55: =+F46/F$40 -> 0.0028901734 | G55: =+G46/G$40 -> 0.0022740193 | H55: =+H46/H$40 -> 0.0054200542 | I55: =+I46/I$40 -> 0.057471264 | J55: =+J46/J$40 -> 0.084781687 | ... Z55: =+Z46/Z$40 -> 0.22346369 | AB55: Others | AC55: =+AC46/AC$40 -> 0.0033039648 | AD55: =+AD46/AD$40 -> 0.0037243948 | AE55: =+AE46/AE$40 -> 0.066553727 | AF55: =+AF46/AF$40 -> 0.079288026 | AI55: Others | AJ55: =+AJ46/AJ$40 -> 0.1612515 | AK55: =+AK46/AK$40 -> 0.13841525 | AL55: =+AL46/AL$40 -> 0.16304348 | AM55: =+AM46/AM$40 -> 0.2259887
B57: m/m
B58: =+B42 -> Hon Hai | D58: =+D42/C42-1 -> 4 | E58: =+E42/D42-1 -> 1.1333333 | F58: =+F42/E42-1 -> 0.25 | G58: =+G42/F42-1 -> 0.25 | H58: =+H42/G42-1 -> 0.4 | I58: =+I42/H42-1 -> 0 | J58: =+J42/I42-1 -> 1.1428571 | K58: =+K42/J42-1 -> 0.73333333 | ... Z58: =+Z42/Y42-1 -> 0 | AB58: Customer Mix Breakdown by Quarter | AI58: Customer Mix Breakdown by Quarter
B59: =+B43 -> Quanta | D59: =+D43/C43-1 -> 0 | E59: =+E43/D43-1 -> 1 | F59: =+F43/E43-1 -> 0.25 | G59: =+G43/F43-1 -> 1.4 | H59: =+H43/G43-1 -> 0.25 | I59: =+I43/H43-1 -> 0.12 | J59: =+J43/I43-1 -> 0.092857143 | K59: =+K43/J43-1 -> 0.47058824 | ... Z59: =+Z43/Y43-1 -> -0.05 | AB59: Hon Hai | AC59: 1Q | AD59: 2Q | AE59: 3Q | AF59: 4Q | AG59: 2025 | AI59: Hon Hai | AJ59: 1Q | AK59: 2Q | AL59: 3Q | AM59: 4Q | AN59: 2026
B60: =+B44 -> Wistron | D60: =+D44/C44-1 -> 0.77777778 | E60: =+E44/D44-1 -> -0.0625 | F60: =+F44/E44-1 -> 1.1333333 | G60: =+G44/F44-1 -> 4.9375 | H60: =+H44/G44-1 -> -0.21052632 | I60: =+I44/H44-1 -> -0.33333333 | J60: =+J44/I44-1 -> -0.7 | K60: =+K44/J44-1 -> 2.9333333 | ... Z60: =+Z44/Y44-1 -> 0 | AB60: Oracle | AC60: 240 | AD60: 950 | AE60: 2500 | AF60: 3200 | AG60: =+SUM(AC60:AF60) -> 6890 | AI60: Oracle | AJ60: 1900 | AK60: 1600 | AL60: 1600 | AM60: 1550 | AN60: =+SUM(AJ60:AM60) -> 6650
B61: =+B45 -> Wiwynn | D61: =+D45/C45-1 -> 1 | E61: =+E45/D45-1 -> 0 | F61: =+F45/E45-1 -> 1.5 | G61: =+G45/F45-1 -> 0 | H61: =+H45/G45-1 -> 1 | I61: =+I45/H45-1 -> 1 | J61: =+J45/I45-1 -> 1.5 | K61: =+K45/J45-1 -> 0 | ... Q61: =+Q45/P45-1 -> -1 | R61: =+IFERROR(R45/Q45-1,"--") -> -- | S61: =+IFERROR(S45/R45-1,"--") -> -- | T61: =+IFERROR(T45/S45-1,"--") -> -- | U61: =+IFERROR(U45/T45-1,"--") -> -- | V61: =+IFERROR(V45/U45-1,"--") -> -- | W61: =+IFERROR(W45/V45-1,"--") -> -- | X61: =+IFERROR(X45/W45-1,"--") -> -- | Y61: =+IFERROR(Y45/X45-1,"--") -> -- | Z61: =+IFERROR(Z45/Y45-1,"--") -> -- | AB61: Microsoft | AC61: 160 | AD61: 550 | AE61: 2000 | AF61: 3100 | AG61: =+SUM(AC61:AF61) -> 5810 | AI61: Microsoft | AJ61: 5000 | AK61: 6600 | AL61: 4600 | AM61: 1800 | AN61: =+SUM(AJ61:AM61) -> 18000
B62: =+B46 -> Others | D62: =+D46/C46-1 -> 0 | E62: =+E46/D46-1 -> 0 | F62: =+F46/E46-1 -> 1 | G62: =+G46/F46-1 -> 1 | H62: =+H46/G46-1 -> 1.5 | I62: =+I46/H46-1 -> 9 | J62: =+J46/I46-1 -> 1 | K62: =+K46/J46-1 -> 0.25 | ... Z62: =+Z46/Y46-1 -> 0 | AB62: Meta | AC62: 0 | AD62: 0 | AE62: 0 | AF62: 100 | AG62: =+SUM(AC62:AF62) -> 100 | AI62: Meta | AJ62: 0 | AK62: 0 | AL62: 200 | AM62: 800 | AN62: =+SUM(AJ62:AM62) -> 1000
B63: Total | D63: =+D40/C40-1 -> 1.2283465 | E63: =+E40/D40-1 -> 0.75971731 | F63: =+F40/E40-1 -> 0.38955823 | G63: =+G40/F40-1 -> 1.5419075 | H63: =+H40/G40-1 -> 0.048891416 | I63: =+I40/H40-1 -> -0.056910569 | J63: =+J40/I40-1 -> 0.35574713 | K63: =+K40/J40-1 -> 0.76557864 | ... Z63: =+Z40/Y40-1 -> -0.0055555556 | AB63: Others | AC63: =+AC64-SUM(AC60:AC62) -> 100 | AD63: =+AD64-SUM(AD60:AD62) -> 100 | AE63: =+AE64-SUM(AE60:AE62) -> 300 | AF63: =+AF64-SUM(AF60:AF62) -> 1400 | AG63: =+SUM(AC63:AF63) -> 1900 | AI63: Others | AJ63: =+AJ64-SUM(AJ60:AJ62) -> 1600 | AK63: =+AK64-SUM(AK60:AK62) -> 1800 | AL63: =+AL64-SUM(AL60:AL62) -> 1100 | AM63: =+AM64-SUM(AM60:AM62) -> 1550 | AN63: =+SUM(AJ63:AM63) -> 6050
AB64: Total | AC64: =+AC42 -> 500 | AD64: =+AD42 -> 1600 | AE64: =+AE42 -> 4800 | AF64: =+AF42 -> 7800 | AG64: =+SUM(AC64:AF64) -> 14700 | AI64: Total | AJ64: =+AJ42 -> 8500 | AK64: =+AK42 -> 10000 | AL64: =+AL42 -> 7500 | AM64: =+AM42 -> 5700 | AN64: =+SUM(AJ64:AM64) -> 31700
B65: y/y
B66: =+B50 -> Mix | O66: =+O42/C42-1 -> 79 | P66: =+P42/D42-1 -> 15 | Q66: =+Q42/E42-1 -> 10.5625 | R66: =+R42/F42-1 -> 8.25 | S66: =+S42/G42-1 -> 5.4 | T66: =+T42/H42-1 -> 3.4285714 | U66: =+U42/I42-1 -> 3.2857143 | V66: =+V42/J42-1 -> 0.66666667 | ... Z66: =+Z42/N42-1 -> -0.28571429 | AB66: Quanta | AC66: 1Q | AD66: 2Q | AE66: 3Q | AF66: 4Q | AG66: 2025 | AI66: Quanta | AJ66: 1Q | AK66: 2Q | AL66: 3Q | AM66: 4Q | AN66: 2026
B67: =+B51 -> Hon Hai | O67: =+O43/C43-1 -> 27.5 | P67: =+P43/D43-1 -> 26 | Q67: =+Q43/E43-1 -> 20.5 | R67: =+R43/F43-1 -> 15.8 | S67: =+S43/G43-1 -> 7.3333333 | T67: =+T43/H43-1 -> 6.2 | U67: =+U43/I43-1 -> 3.5238095 | V67: =+V43/J43-1 -> 2.9215686 | ... Z67: =+Z43/N43-1 -> -0.71212121 | AB67: Google | AC67: 100 | AD67: 215 | AE67: 300 | AF67: 1112 | AG67: =+SUM(AC67:AF67) -> 1727 | AI67: Google | AJ67: 2300 | AK67: 500 | AL67: 400 | AM67: 0 | AN67: =+SUM(AJ67:AM67) -> 3200
B68: =+B52 -> Quanta | O68: =+O44/C44-1 -> 20.111111 | P68: =+P44/D44-1 -> 17.125 | Q68: =+Q44/E44-1 -> 19.666667 | R68: =+R44/F44-1 -> 7.28125 | S68: =+S44/G44-1 -> 0.47368421 | T68: =+T44/H44-1 -> 0.93333333 | U68: =+U44/I44-1 -> 1.4 | V68: =+V44/J44-1 -> 5.6666667 | ... Z68: =+Z44/N44-1 -> 0.17647059 | AB68: Amazon | AC68: 20 | AD68: 45 | AE68: 412 | AF68: 467 | AG68: =+SUM(AC68:AF68) -> 944 | AI68: Amazon | AJ68: 1000 | AK68: 4400 | AL68: 2800 | AM68: 1000 | AN68: =+SUM(AJ68:AM68) -> 9200
B69: =+B53 -> Wistron | O69: =+O45/C45-1 -> 19 | P69: =+P45/D45-1 -> 14 | Q69: =+Q45/E45-1 -> -1 | R69: =+R45/F45-1 -> -1 | S69: =+S45/G45-1 -> -1 | T69: =+T45/H45-1 -> -1 | U69: =+U45/I45-1 -> -1 | V69: =+V45/J45-1 -> -1 | ... Z69: =+Z45/N45-1 -> -1 | AB69: Meta | AC69: 80 | AD69: 540 | AE69: 842 | AF69: 1541 | AG69: =+SUM(AC69:AF69) -> 3003 | AI69: Meta | AJ69: 1400 | AK69: 1200 | AL69: 800 | AM69: 400 | AN69: =+SUM(AJ69:AM69) -> 3800
B70: =+B54 -> Wiwynn | O70: =+O46/C46-1 -> 1149 | P70: =+P46/D46-1 -> 1099 | Q70: =+Q46/E46-1 -> 1099 | R70: =+R46/F46-1 -> 574 | S70: =+S46/G46-1 -> 286.5 | T70: =+T46/H46-1 -> 114 | U70: =+U46/I46-1 -> 9 | V70: =+V46/J46-1 -> 4 | ... Z70: =+Z46/N46-1 -> 1.3529412 | AB70: Others | AC70: =+AC71-SUM(AC67:AC69) -> 0 | AD70: =+AD71-SUM(AD67:AD69) -> 0 | AE70: =+AE71-SUM(AE67:AE69) -> 0 | AF70: =+AF71-SUM(AF67:AF69) -> 450 | AG70: =+AG71-SUM(AG67:AG69) -> 450 | AI70: Oracle | AJ70: =+AJ71-SUM(AJ67:AJ69) -> 225 | AK70: =+AK71-SUM(AK67:AK69) -> 1200 | AL70: =+AL71-SUM(AL67:AL69) -> 900 | AM70: =+AM71-SUM(AM67:AM69) -> 175 | AN70: =+AN71-SUM(AN67:AN69) -> 2500
B71: Total | O71: =+O40/C40-1 -> 45.811024 | P71: =+P40/D40-1 -> 21.367491 | Q71: =+Q40/E40-1 -> 16.068273 | R71: =+R40/F40-1 -> 10.958092 | S71: =+S40/G40-1 -> 3.6901649 | T71: =+T40/H40-1 -> 3.5528455 | U71: =+U40/I40-1 -> 3.0804598 | V71: =+V40/J40-1 -> 1.6706231 | ... Z71: =+Z40/N40-1 -> -0.23959218 | AB71: Total | AC71: =+AC43 -> 200 | AD71: =+AD43 -> 800 | AE71: =+AE43 -> 1554 | AF71: =+AF43 -> 3570 | AG71: =+SUM(AC71:AF71) -> 6124 | AI71: Total | AJ71: =+AJ43 -> 4925 | AK71: =+AK43 -> 7300 | AL71: =+AL43 -> 4900 | AM71: =+AM43 -> 1575 | AN71: =+SUM(AJ71:AM71) -> 18700
AB73: Wistron | AC73: 1Q | AD73: 2Q | AE73: 3Q | AF73: 4Q | AG73: 2025 | AI73: Wistron | AJ73: 1Q | AK73: 2Q | AL73: 3Q | AM73: 4Q | AN73: 2026
AB74: xAI | AC74: 200 | AD74: 1300 | AE74: 400 | AF74: 650 | AG74: =+SUM(AC74:AF74) -> 2550 | AI74: xAI | AJ74: 1000 | AK74: 1500 | AL74: 1000 | AM74: 1000 | AN74: =+SUM(AJ74:AM74) -> 4500
AB75: Coreweave | AC75: 0 | AD75: 560 | AE75: 800 | AF75: 1040 | AG75: =+SUM(AC75:AF75) -> 2400 | AI75: Coreweave | AJ75: 1200 | AK75: 1000 | AL75: 800 | AM75: 500 | AN75: =+SUM(AJ75:AM75) -> 3500
AB76: Oracle | AC76: 0 | AD76: 0 | AE76: 0 | AF76: 400 | AG76: =+SUM(AC76:AF76) -> 400 | AI76: Oracle | AJ76: 0 | AK76: 0 | AL76: 0 | AN76: =+SUM(AJ76:AM76) -> 0
AB77: Others | AC77: =+AC78-SUM(AC74:AC76) -> 0 | AD77: =+AD78-SUM(AD74:AD76) -> 0 | AE77: =+AE78-SUM(AE74:AE76) -> 40 | AF77: =+AF78-SUM(AF74:AF76) -> 335 | AG77: =+SUM(AC77:AF77) -> 375 | AI77: Others | AJ77: =+AJ78-SUM(AJ74:AJ76) -> 1750 | AK77: =+AK78-SUM(AK74:AK76) -> 1675 | AL77: =+AL78-SUM(AL74:AL76) -> 1200 | AM77: =+AM78-SUM(AM74:AM76) -> 1500 | AN77: =+SUM(AJ77:AM77) -> 6125
AB78: Total | AC78: =+AC44 -> 200 | AD78: =+AD44 -> 1860 | AE78: =+AE44 -> 1240 | AF78: =+AF44 -> 2425 | AG78: =+SUM(AC78:AF78) -> 5725 | AI78: Total | AJ78: =+AJ44 -> 3950 | AK78: =+AK44 -> 4175 | AL78: =+AL44 -> 3000 | AM78: =+AM44 -> 3000 | AN78: =+SUM(AJ78:AM78) -> 14125
D150: 8.05
P159: 0.4 | Q159: 1.26

Sheet NVL72 BoM Comparison
B4: Nvidia NVL72 Bill of Materials | C4: GB200 | D4: GB300 | E4: VR200 | G4: Diff. | X4: ODM Value-Add per rack | Y4: GB200 | Z4: GB300 | AA4: VR200
B5: GPU | C5: =+'GB200 BoM'!C32 -> 2160000 | D5: =+'GB300 BoM'!C32 -> 2520000 | E5: =+'VR200 BoM '!C33 -> 3960000 | G5: =+E5/D5-1 -> 0.57142857 | X5: Compute Board Assembly/Test | Y5: =+'GB200 BoM'!I10*(1-70%)*36 -> 12096 | Z5: =+'GB300 BoM'!I10*(1-70%)*36 -> 12096 | AA5: =+'VR200 BoM '!I10*(1-70%)*36 -> 16200
B6: CPU | C6: =5000*36 -> 180000 | D6: =5000*36 -> 180000 | E6: =+'VR200 BoM '!C34 -> 198000 | G6: =+E6/D6-1 -> 0.1 | X6: Compute Tray Assembly/Test | Y6: =+'GB200 BoM'!F14*18 -> 28800 | Z6: =+'GB300 BoM'!F15*18 -> 28800 | AA6: =+'VR200 BoM '!F16*18 -> 32400
B7: NVLink Switch chip | C7: =+'GB200 BoM'!C34 -> 64800 | D7: =+'GB300 BoM'!C34 -> 64800 | E7: =4000*4*9 -> 144000 | G7: =+E7/D7-1 -> 1.2222222 | X7: Switch Board Assembly/Test | Y7: =+'GB200 BoM'!I23*9 -> 2475 | Z7: =+'GB300 BoM'!I23*9 -> 2475 | AA7: =+'VR200 BoM '!I24*9 -> 3150
B8: Other networking chips | C8: =+('GB200 BoM'!F5+'GB200 BoM'!F6)*18 -> 162000 | D8: =+('GB300 BoM'!F5+'GB300 BoM'!F6)*18 -> 261000 | E8: =+('VR200 BoM '!F5+'VR200 BoM '!F6)*18 -> 576000 | G8: =+E8/D8-1 -> 1.2068966 | X8: Switch Tray Assembly/Test | Y8: =+'GB200 BoM'!F24*(1-70%)*9 -> 2700 | Z8: =+'GB300 BoM'!F26*(1-70%)*9 -> 2700 | AA8: =+'VR200 BoM '!F26*(1-70%)*9 -> 3150
B9: Memory | C9: =+'GB200 BoM'!C35 -> 232992 | D9: =+'GB300 BoM'!C35 -> 373939.2 | E9: =+'VR200 BoM '!C36 -> 2001600 | G9: =+E9/D9-1 -> 4.3527418 | X9: Rack Assembly/Test | Y9: =+C16 -> 25600 | Z9: =+D16 -> 22400 | AA9: =+E16 -> 28800
B10: Cooling | C10: =+'GB200 BoM'!C39 -> 55790 | D10: =+'GB300 BoM'!C39 -> 64610 | E10: =+'VR200 BoM '!C40 -> 72080 | G10: =+E10/D10-1 -> 0.11561678 | X10: BF DPU Assembly/Test | Y10: =65*18 -> 1170 | Z10: =65*18 -> 1170 | AA10: =65*18 -> 1170
B11: Power supply | C11: =+'GB200 BoM'!C40 -> 36000 | D11: =+'GB300 BoM'!C40 -> 57600 | E11: =+'VR200 BoM '!C41 -> 76000 | G11: =+E11/D11-1 -> 0.31944444 | X11: CX/Orchid Module Assembly/Test | Y11: 0 | Z11: 0 | AA11: =50*72 -> 3600
B12: PCB | C12: =+'GB200 BoM'!C36 -> 34200 | D12: =+'GB300 BoM'!C36 -> 35100 | E12: =+'VR200 BoM '!C37 -> 116730 | G12: =+E12/D12-1 -> 2.325641 | X12: Other peripheral boards | Y12: =35*90 -> 3150 | Z12: =35*90 -> 3150 | AA12: =35*36 -> 1260
B13: ABF Substrate | C13: =+'GB200 BoM'!C37 -> 11160 | D13: =+'GB300 BoM'!C37 -> 11160 | E13: =+'VR200 BoM '!C38 -> 20340 | G13: =+E13/D13-1 -> 0.82258065 | X13: Cooling components | Y13: =20%*C10 -> 11158 | Z13: =20%*D10 -> 12922 | AA13: =20%*E10 -> 14416
B14: MLCC | C14: =+'GB200 BoM'!C38 -> 1710 | D14: =+'GB300 BoM'!C38 -> 1530 | E14: =+'VR200 BoM '!C39 -> 4320 | G14: =+E14/D14-1 -> 1.8235294 | X14: Others | Y14: 18500 | Z14: 22500 | AA14: 45500
B15: Others | C15: =+C17-C16-SUM(C5:C14) -> 365270.67 | D15: =+D17-D16-SUM(D5:D14) -> 402411.67 | E15: =+E17-E16-SUM(E5:E14) -> 605277.67 | G15: =+E15/D15-1 -> 0.50412554 | X15: Total ODM Value-Add | Y15: =SUM(Y5:Y14) -> 105649 | Z15: =SUM(Z5:Z14) -> 108213 | AA15: =SUM(AA5:AA14) -> 149646
B16: Rack assembly value add | C16: =+'GB200 BoM'!C13 -> 25600 | D16: =+'GB300 BoM'!C13 -> 22400 | E16: =+'VR200 BoM '!C44 -> 28800 | G16: =+E16/D16-1 -> 0.28571429 | X16: Total ODM Value-Add (%) | Y16: =+Y15/C17 -> 0.031730975 | Z16: =+Z15/D17 -> 0.027090154 | AA16: =+AA15/E17 -> 0.019177646
B17: Total | C17: =+'GB200 BoM'!C14 -> 3329522.7 | D17: =+'GB300 BoM'!C14 -> 3994550.9 | E17: =+'VR200 BoM '!C14 -> 7803147.7 | G17: =+E17/D17-1 -> 0.95344807 | X17: Difference | Z17: =+Z15/Y15-1 -> 0.024269042 | AA17: =+AA15/Z15-1 -> 0.38288376
B18: Difference | D18: =+D17/C17-1 -> 0.1997368 | E18: =+E17/D17-1 -> 0.95344807
X19: PCB ASP per board (US$) | Y19: GB200 | Z19: GB300 | AA19: VR200
B20: =+B4 -> Nvidia NVL72 Bill of Materials | C20: =+C4 -> GB200 | D20: =+D4 -> GB300 | E20: =+E4 -> VR200 | X20: Compute PCB | Y20: =+'GB200 BoM'!I8*30% -> 650 | Z20: =+'GB300 BoM'!I8*30% -> 650 | AA20: =+'VR200 BoM '!I8*30% -> 1400
B21: =+B5 -> GPU | C21: =+C5/C$17 -> 0.64874164 | D21: =+D5/D$17 -> 0.63085941 | E21: =+E5/E$17 -> 0.50748751 | X21: Switch PCB | Y21: =+'GB200 BoM'!I21*30% -> 700 | Z21: =+'GB300 BoM'!I21*30% -> 800 | AA21: =+'VR200 BoM '!I22*30% -> 1450
B22: =+B6 -> CPU | C22: =+C6/C$17 -> 0.054061803 | D22: =+D6/D$17 -> 0.045061386 | E22: =+E6/E$17 -> 0.025374376 | X22: Midplane PCB | Y22: 0 | Z22: 0 | AA22: =+'VR200 BoM '!F8*0.75 -> 1500
B23: =+B7 -> NVLink Switch chip | C23: =+C7/C$17 -> 0.019462249 | D23: =+D7/D$17 -> 0.016222099 | E23: =+E7/E$17 -> 0.018454091 | X23: BlueField PCB | Y23: 0 | Z23: 0 | AA23: =+'VR200 BoM '!F30 -> 255
B24: =+B8 -> Other networking chips | C24: =+C8/C$17 -> 0.048655623 | D24: =+D8/D$17 -> 0.06533901 | E24: =+E8/E$17 -> 0.073816365 | X24: ConnectX PCB | Y24: 0 | Z24: 0 | AA24: =+'VR200 BoM '!F31 -> 270
B25: =+B9 -> Memory | C25: =+C9/C$17 -> 0.069977598 | D25: =+D9/D$17 -> 0.093612327 | E25: =+E9/E$17 -> 0.25651187 | X25: Other peripheral PCB | Y25: =+'GB200 BoM'!F28 -> 50 | Z25: =+'GB300 BoM'!F30 -> 50 | AA25: =+'VR200 BoM '!F32 -> 50
B26: =+B10 -> Cooling | C26: =+C10/C$17 -> 0.016756156 | D26: =+D10/D$17 -> 0.016174534 | E26: =+E10/E$17 -> 0.009237298 | X26: PCB Units per rack | Y26: GB200 | Z26: GB300 | AA26: VR200
B27: =+B11 -> Power supply | C27: =+C11/C$17 -> 0.010812361 | D27: =+D11/D$17 -> 0.014419644 | E27: =+E11/E$17 -> 0.0097396593 | X27: =+X20 -> Compute PCB | Y27: 36 | Z27: 36 | AA27: 36
B28: =+B12 -> PCB | C28: =+C12/C$17 -> 0.010271743 | D28: =+D12/D$17 -> 0.0087869703 | E28: =+E12/E$17 -> 0.014959348 | X28: =+X21 -> Switch PCB | Y28: 9 | Z28: 9 | AA28: 9
B29: =+B13 -> ABF Substrate | C29: =+C13/C$17 -> 0.0033518318 | D29: =+D13/D$17 -> 0.002793806 | E29: =+E13/E$17 -> 0.0026066404 | X29: =+X22 -> Midplane PCB | Y29: 0 | Z29: 0 | AA29: 18
B30: =+B14 -> MLCC | C30: =+C14/C$17 -> 0.00051358713 | D30: =+D14/D$17 -> 0.00038302178 | E30: =+E14/E$17 -> 0.00055362274 | X30: =+X23 -> BlueField PCB | Y30: 18 | Z30: 18 | AA30: 18
X31: =+X24 -> ConnectX PCB | Y31: 0 | Z31: 0 | AA31: 72
B32: =+B15 -> Others | C32: =+C15/C$17 -> 0.10970662 | D32: =+D15/D$17 -> 0.10074015 | E32: =+E15/E$17 -> 0.077568398 | X32: =+X25 -> Other peripheral PCB | Y32: 90 | Z32: 90 | AA32: 45
B33: =+B16 -> Rack assembly value add | C33: =+C16/C$17 -> 0.0076887898 | D33: =+D16/D$17 -> 0.0056076392 | E33: =+E16/E$17 -> 0.0036908183 | X33: Total PCB Content per rack | Y33: GB200 | Z33: GB300 | AA33: VR200
B34: =+B17 -> Total | C34: =+C17/C$17 -> 1 | D34: =+D17/D$17 -> 1 | E34: =+E17/E$17 -> 1 | X34: =+X20 -> Compute PCB | Y34: =+Y20*Y27 -> 23400 | Z34: =+Z20*Z27 -> 23400 | AA34: =+AA20*AA27 -> 50400
X35: =+X21 -> Switch PCB | Y35: =+Y21*Y28 -> 6300 | Z35: =+Z21*Z28 -> 7200 | AA35: =+AA21*AA28 -> 13050
B36: Cooling content (US$) | C36: =+C4 -> GB200 | D36: =+D4 -> GB300 | E36: =+E4 -> VR200 | X36: =+X22 -> Midplane PCB | Y36: =+Y22*Y29 -> 0 | Z36: =+Z22*Z29 -> 0 | AA36: =+AA22*AA29 -> 27000
B37: Cooling (In-tray only) | C37: =+C10-'GB200 BoM'!C7-'GB200 BoM'!C10 -> 41490 | D37: =+D10-'GB300 BoM'!C7-'GB300 BoM'!C10 -> 50310 | E37: =+E10-'VR200 BoM '!C7-'VR200 BoM '!C10 -> 57780 | X37: =+X23 -> BlueField PCB | Y37: =+Y23*Y30 -> 0 | Z37: =+Z23*Z30 -> 0 | AA37: =+AA23*AA30 -> 4590
B38: Rack Manifold | C38: =+'GB200 BoM'!C7 -> 13500 | D38: =+'GB300 BoM'!C7 -> 13500 | E38: =+'VR200 BoM '!C7 -> 13500 | X38: =+X24 -> ConnectX PCB | Y38: =+Y24*Y31 -> 0 | Z38: =+Z24*Z31 -> 0 | AA38: =+AA24*AA31 -> 19440
B39: Rack-level other cooling | C39: =+'GB200 BoM'!C10 -> 800 | D39: =+'GB300 BoM'!C10 -> 800 | E39: =+'VR200 BoM '!C10 -> 800 | X39: =+X25 -> Other peripheral PCB | Y39: =+Y25*Y32 -> 4500 | Z39: =+Z25*Z32 -> 4500 | AA39: =+AA25*AA32 -> 2250
B40: Total cooling (ex-Side-car CDU) | C40: =SUM(C35:C39) -> 55790 | D40: =SUM(D35:D39) -> 64610 | E40: =SUM(E35:E39) -> 72080 | X40: Total PCB Content per rack | Y40: =+SUM(Y34:Y39) -> 34200 | Z40: =+SUM(Z34:Z39) -> 35100 | AA40: =+SUM(AA34:AA39) -> 116730
B41: Side-car CDU | C41: 50000 | D41: 50000 | E41: 50000 | X41: Difference | Z41: =+Z40/Y40-1 -> 0.026315789 | AA41: =+AA40/Z40-1 -> 2.325641
B42: Total cooling | C42: =SUM(C37:C41) -> 161580 | D42: =SUM(D40:D41) -> 114610 | E42: =SUM(E37:E41) -> 194160
X43: ABF Substrate ASP per chip (US$) | Y43: GB200 | Z43: GB300 | AA43: VR200
X44: GPU | Y44: 100 | Z44: 100 | AA44: 200
X45: CPU | Y45: 50 | Z45: 50 | AA45: 60
X46: NVSwitch ASIC | Y46: 30 | Z46: 30 | AA46: 30
X47: BlueField DPU | Y47: 30 | Z47: 30 | AA47: 30
X48: ConnectX chip | Y48: 30 | Z48: 30 | AA48: 30
X49: ABF Units per rack | Y49: GB200 | Z49: GB300 | AA49: VR200
X50: =+X44 -> GPU | Y50: 72 | Z50: 72 | AA50: 72
X51: =+X45 -> CPU | Y51: 36 | Z51: 36 | AA51: 36
X52: =+X46 -> NVSwitch ASIC | Y52: =2*9 -> 18 | Z52: =2*9 -> 18 | AA52: =4*9 -> 36
X53: =+X47 -> BlueField DPU | Y53: =1*18 -> 18 | Z53: 18 | AA53: 18
X54: =+X48 -> ConnectX chip | Y54: =2*18 -> 36 | Z54: =2*18 -> 36 | AA54: =4*18 -> 72
X55: Total ABF Content per rack | Y55: GB200 | Z55: GB300 | AA55: VR200
X56: =+X44 -> GPU | Y56: =+Y44*Y50 -> 7200 | Z56: =+Z44*Z50 -> 7200 | AA56: =+AA44*AA50 -> 14400
X57: =+X45 -> CPU | Y57: =+Y45*Y51 -> 1800 | Z57: =+Z45*Z51 -> 1800 | AA57: =+AA45*AA51 -> 2160
X58: =+X46 -> NVSwitch ASIC | Y58: =+Y46*Y52 -> 540 | Z58: =+Z46*Z52 -> 540 | AA58: =+AA46*AA52 -> 1080
X59: =+X47 -> BlueField DPU | Y59: =+Y47*Y53 -> 540 | Z59: =+Z47*Z53 -> 540 | AA59: =+AA47*AA53 -> 540
X60: =+X48 -> ConnectX chip | Y60: =+Y48*Y54 -> 1080 | Z60: =+Z48*Z54 -> 1080 | AA60: =+AA48*AA54 -> 2160
X61: Total ABF Content per rack | Y61: =+SUM(Y56:Y60) -> 11160 | Z61: =+SUM(Z56:Z60) -> 11160 | AA61: =+SUM(AA56:AA60) -> 20340
X62: Difference | Z62: =+Z61/Y61-1 -> 0 | AA62: =+AA61/Z61-1 -> 0.82258065
X64: MLCC content per board (US$) | Y64: GB200 | Z64: GB300 | AA64: VR200
X65: Compute PCB | Y65: 30 | Z65: 25 | AA65: 90
X66: Switch PCB | Y66: 20 | Z66: 20 | AA66: 45
X67: BlueField DPU Module | Y67: 15 | Z67: 5 | AA67: 5
X68: ConnectX Orchid Module | Y68: 15 | Z68: 5 | AA68: 5
X69: Other peripheral PCB | Y69: 10 | Z69: 5 | AA69: 5
X70: Units per rack | Y70: GB200 | Z70: GB300 | AA70: VR200
X71: =+X65 -> Compute PCB | Y71: 36 | Z71: 36 | AA71: 36
X72: =+X66 -> Switch PCB | Y72: 9 | Z72: 9 | AA72: 9
X73: =+X67 -> BlueField DPU Module | Y73: 0 | Z73: 0 | AA73: 18
X74: =+X68 -> ConnectX Orchid Module | Y74: 0 | Z74: 0 | AA74: 72
X75: =+X69 -> Other peripheral PCB | Y75: 90 | Z75: 90 | AA75: 45
X76: Total MLCC Content per rack | Y76: GB200 | Z76: GB300 | AA76: VR200
X77: =+X65 -> Compute PCB | Y77: =+Y65*Y71 -> 1080 | Z77: =+Z65*Z71 -> 900 | AA77: =+AA65*AA71 -> 3240
X78: =+X66 -> Switch PCB | Y78: =+Y66*Y72 -> 180 | Z78: =+Z66*Z72 -> 180 | AA78: =+AA66*AA72 -> 405
X79: =+X67 -> BlueField DPU Module | Y79: =+Y67*Y73 -> 0 | Z79: =+Z67*Z73 -> 0 | AA79: =+AA67*AA73 -> 90
X80: =+X68 -> ConnectX Orchid Module | Y80: =+Y68*Y74 -> 0 | Z80: =+Z68*Z74 -> 0 | AA80: =+AA68*AA74 -> 360
X81: =+X69 -> Other peripheral PCB | Y81: =+Y69*Y75 -> 900 | Z81: =+Z69*Z75 -> 450 | AA81: =+AA69*AA75 -> 225
X82: Total MLCC Content per rack | Y82: =+SUM(Y77:Y81) -> 2160 | Z82: =+SUM(Z77:Z81) -> 1530 | AA82: =+SUM(AA77:AA81) -> 4320
X83: Difference | Z83: =+Z82/Y82-1 -> -0.29166667 | AA83: =+AA82/Z82-1 -> 1.8235294

Sheet VR200 BoM 
B2: VR200 NVL72
B3: VR200 NVL72 Bill of materials (US$) | E3: Compute Tray | F3: =SUM(F4:F17) -> 407228 | P3: # of BMC
B4: 18x Compute Tray | C4: =+F3*18 -> 7330104 | E4: Compute board (2x) | F4: =+I4*2 -> 343039.33 | H4: Compute board | I4: =+SUM(I5:I11) -> 171519.67 | O4: NVL36 | P4: 41
B5: 9x Switch Tray | C5: =+F19*9 -> 239277 | E5: BF4 DPU Module | F5: 10000 | H5: Vera (1x) | I5: 5500 | K5: R200 ASP | O5: NVL72 | P5: 85 | S5: 1x Cable Cartridge | T5: ASP (US$) | U5: Total (US$)
B6: Rack Chassis | C6: 3000 | E6: CX9 NIC | F6: =5500*4 -> 22000 | H6: R200 (2x) | I6: =+K6*2 -> 110000 | K6: 55000 | S6: 36x NVLink Male | T6: 25 | U6: =+T6*36 -> 900
B7: Manifold (CDM) | C7: 13500 | E7: Storage | F7: =+T29+(T28*4) -> 23072 | H7: Cold Plate (2x) | I7: =400 -> 400 | O7: GB300 | P7: 71 | S7: Cables | T7: 1250 | U7: =+T7*1 -> 1250
B8: Power supply | C8: 76000 | E8: Midplane PCB | F8: 2000 | H8: PCB (HDI) | I8: =1400/(1-70%) -> 4666.6667 | O8: VR200 | P8: 80 | S8: Spine chassis | T8: 150 | U8: =+T8*1 -> 150
B9: Management switch | C9: =2000*2 -> 4000 | E9: Paladin connectors | F9: =+V35 -> 2066.6667 | H9: SOCAMM (8x per board) | I9: =(T26*8)/(1-70%) -> 43520 | S9: Total | U9: =SUM(U6:U8) -> 2300
B10: Other cooling | C10: 800 | E10: NVQD (20x) | F10: =20*20 -> 400 | H10: Assembly/Test | I10: =450/(1-70%) -> 1500 | S10: Nvidia margin | U10: 0.7
B11: 4x Cable Cartridge | C11: =+U12 -> 30666.667 | E11: Inner Manifold | F11: 1000 | H11: Others | I11: =5000+933 -> 5933 | S11: ASP in BOM | U11: =+U9/(1-U10) -> 7666.6667
B12: Others | C12: 77000 | E12: Cold Plate (3x) | F12: =150*3 -> 450 | S12: 4x Cable Cartridge | U12: =+U11*4 -> 30666.667
B13: Rack assembly & test | C13: 28800 | E13: Floating mount | F13: =50*2 -> 100
B14: Total | C14: =+SUM(C4:C13) -> 7803147.7 | E14: Chassis | F14: 250
E15: Railkit | F15: 50
B16: =+B3 -> VR200 NVL72 Bill of materials (US$) | E16: Assembly/Test | F16: 1800
B17: =+B4 -> 18x Compute Tray | C17: =+C4/C$14 -> 0.93937784 | E17: Others | F17: 1000
B18: =+B5 -> 9x Switch Tray | C18: =+C5/C$14 -> 0.030664164
B19: =+B6 -> Rack Chassis | C19: =+C6/C$14 -> 0.00038446024 | E19: Switch Tray | F19: =SUM(F20:F27) -> 26586.333
B20: =+B7 -> Manifold (CDM) | C20: =+C7/C$14 -> 0.0017300711 | E20: Switch board | F20: =+I20 -> 23066.333 | H20: Switch board | I20: =+SUM(I21:I25) -> 23066.333
B21: =+B8 -> Power supply | C21: =+C8/C$14 -> 0.0097396593 | E21: Chassis | F21: 250 | H21: NVLink switch chip (4x) | I21: =+K23*4 -> 16000
B22: =+B9 -> Management switch | C22: =+C9/C$14 -> 0.00051261365 | E22: Floating mount & others | F22: =50*2+60 -> 160 | H22: PCB (MLB) | I22: =1450/(1-70%) -> 4833.3333 | K22: NVLink switch chip ASP
B23: =+B10 -> Other cooling | C23: =+C10/C$14 -> 0.00010252273 | E23: NVQD (18x) | F23: =20*18 -> 360 | H23: Cold Plate (2x) | I23: =200*2 -> 400 | K23: 4000
B24: =+B11 -> 4x Cable Cartridge | C24: =+C11/C$14 -> 0.003930038 | E24: Railkit | F24: 50 | H24: Assembly/Test | I24: 350
B25: =+B12 -> Others | C25: =+C12/C$14 -> 0.0098678127 | E25: Paladin connectors | F25: =+V42 -> 533.33333 | H25: Others | I25: =550+933 -> 1483 | S25: Memory (ex-HBM) | T25: ASP (US$) | U25: Total (US$)
B26: =+B13 -> Rack assembly & test | C26: =+C13/C$14 -> 0.0036908183 | E26: Assembly/Test | F26: =350/(1-70%) -> 1166.6667 | S26: 288x 192GB SOCAMM | T26: =192*8*1.0625 -> 1632 | U26: =+T26*288/(1-70%) -> 1566720
B27: =+B14 -> Total | C27: =+SUM(C17:C26) -> 1 | E27: Others | F27: 1000 | S27: LPDDR5X 128GB (BF4) | T27: =128*8*1.0625 -> 1088 | U27: =+T27*18 -> 19584
S28: E1.S NVMe SSD (16TB) | T28: =350*16 -> 5600 | U28: =+T28*72 -> 403200
E29: Peripheral PCB boards | F29: =+F30*18+F31*72+F32*36 -> 25830 | H29: ABF Substrate Content per Rack | I29: =SUM(I30:I34) -> 20340 | K29: MLCC Content per Rack | L29: =SUM(L30:L34) -> 4320 | S29: M.2 SSD (1.92TB) | T29: =350*1.92 -> 672 | U29: =+T29*18 -> 12096
E30: BF4-Module (18x, 1x per compute tray) | F30: 255 | H30: R200 ($200 each, 72x per rack) | I30: =200*72 -> 14400 | K30: Strata ($90 per board, 36x boards) | L30: =90*36 -> 3240 | S30: Total | U30: =SUM(U26:U29) -> 2001600
E31: CX9-Orchid Module (72x, 4x per compute tray) | F31: 270 | H31: Vera ($60 each, 36x per rack) | I31: =60*36 -> 2160 | K31: Switch board ($45 per board, 9x boards) | L31: =45*9 -> 405
B32: Simplied VR200 NVL72 BOM | E32: Other peripheral boards (45x) | F32: 50 | H32: NVLink ($30 each, 36x per rack) | I32: =30*36 -> 1080 | K32: BlueField Module ($5 per board, 18x boards) | L32: =5*18 -> 90
B33: Rubin GPU | C33: =+K6*72 -> 3960000 | H33: BlueField ($30 each, 18x per rack) | I33: =30*18 -> 540 | K33: CX9 Orchid Module ($5 per board, 72x boards) | L33: =5*72 -> 360
B34: Vera CPU | C34: =+I5*36 -> 198000 | H34: CX ($30 each, 72x per rack) | I34: =30*72 -> 2160 | K34: Peripheral boards ($5 per board, 45x boards) | L34: =5*45 -> 225 | S34: Paladin connectors | T34: Quantity | U34: ASP (US$) | V34: Total (US$)
B35: Networking chips | C35: =(4*9*K23)+((F5-700)*18)+((F6-700)*18) -> 694800 | S35: Compute tray | T35: =SUM(T36:T41) -> 28 | U35: =+V35/T35 -> 73.809524 | V35: =SUM(V36:V41) -> 2066.6667
B36: Memory | C36: =+(I9*2+F7)*18+(T27*18) -> 2001600 | S36: 4x NVLink Female | T36: 4 | U36: 20 | V36: =+(U36*T36)/(1-70%) -> 266.66667
B37: PCB | C37: =+(I8*0.3*36)+(F8*0.75*18)+(F30*18)+(F31*72)+(I22*0.3*9)+(F32*45) -> 116730 | S37: 6x Board2Board Female (Compute board) | T37: 6 | U37: 20 | V37: =+(U37*T37)/(1-70%) -> 400
B38: ABF Substrate | C38: =+I29 -> 20340 | S38: 1x Board2Board Female (BF4) | T38: 1 | U38: 20 | V38: =+(U38*T38)/(1-70%) -> 66.666667
B39: MLCC | C39: =+L29 -> 4320 | S39: 4x Board2Board Female (CX9) | T39: 4 | U39: 20 | V39: =+(U39*T39)/(1-70%) -> 266.66667
B40: Cooling | C40: =+((F10+F11+F12+F13)*18)+(I7*36)+(I23*9)+((F22+F23)*9)+C7+C10 -> 72080 | S40: 1x Board2Board Female | T40: 1 | U40: 20 | V40: =+(U40*T40)/(1-70%) -> 66.666667
B41: Power supply | C41: =+C8 -> 76000 | S41: 12x Board2Board Male (Midplane) | T41: 12 | U41: 25 | V41: =+(U41*T41)/(1-70%) -> 1000
B42: Chassis/Rail kits | C42: =+(F14+F15)*18+(F21+F24)*9+C6 -> 11100 | S42: Switch tray | T42: =SUM(T43) -> 8 | U42: =+V42/T42 -> 66.666667 | V42: =SUM(V43) -> 533.33333
B43: Others | C43: =+C45-C44-SUM(C33:C42) -> 619377.67 | S43: 8x NVLink Female | T43: 8 | U43: 20 | V43: =+(U43*T43)/(1-70%) -> 533.33333
B44: Rack assembly value add | C44: =+C13 -> 28800 | S44: Cartridge | T44: =SUM(T45) -> 36 | U44: =+V44/T44 -> 83.333333 | V44: =SUM(V45) -> 3000
B45: Total | C45: =+C14 -> 7803147.7 | S45: 36x NVLink Male | T45: 36 | U45: 25 | V45: =+(U45*T45)/(1-70%) -> 3000
B47: =+B32 -> Simplied VR200 NVL72 BOM | S47: Total | T47: =+SUM(T48:T50) -> 720 | U47: =+V47/T47 -> 75 | V47: =+SUM(V48:V50) -> 54000
B48: =+B33 -> Rubin GPU | C48: =+C33/C$45 -> 0.50748751 | S48: 18x Compute tray | T48: =+T35*18 -> 504 | U48: =+U35 -> 73.809524 | V48: =+T48*U48 -> 37200
B49: =+B34 -> Vera CPU | C49: =+C34/C$45 -> 0.025374376 | S49: 9x Switch tray | T49: =+T42*9 -> 72 | U49: =+U42 -> 66.666667 | V49: =+T49*U49 -> 4800
B50: =+B35 -> Networking chips | C50: =+C35/C$45 -> 0.089040991 | S50: 4x Cartridge | T50: =+T44*4 -> 144 | U50: =+U44 -> 83.333333 | V50: =+T50*U50 -> 12000
B51: =+B36 -> Memory | C51: =+C36/C$45 -> 0.25651187
B52: =+B37 -> PCB | C52: =+C37/C$45 -> 0.014959348
B53: =+B38 -> ABF Substrate | C53: =+C38/C$45 -> 0.0026066404
B54: =+B39 -> MLCC | C54: =+C39/C$45 -> 0.00055362274
B55: =+B40 -> Cooling | C55: =+C40/C$45 -> 0.009237298
B56: =+B41 -> Power supply | C56: =+C41/C$45 -> 0.0097396593
B57: =+B42 -> Chassis/Rail kits | C57: =+C42/C$45 -> 0.0014225029
B58: =+B43 -> Others | C58: =+C43/C$45 -> 0.079375361
B59: =+B44 -> Rack assembly value add | C59: =+C44/C$45 -> 0.0036908183
B60: =+B45 -> Total | C60: =+C45/C$45 -> 1

Sheet GB300 BoM
B2: GB300 NVL72
B3: GB300 NVL72 Bill of materials (US$) | E3: Compute Tray | F3: =SUM(F4:F16) -> 205131.07 | P3: # of BMC
B4: 18x Compute Tray | C4: =+F3*18 -> 3692359.2 | E4: Compute board (2x) | F4: =+I4*2 -> 182073.33 | H4: Compute board | I4: =+SUM(I5:I11) -> 91036.667 | O4: NVL36 | P4: 41
B5: 9x Switch Tray | C5: =+F18*9 -> 131025 | E5: BF3 DPU Module | F5: 5500 | H5: Grace (1x) | I5: 5000 | K5: B300 ASP | O5: NVL72 | P5: 85 | S5: 1x Cable Cartridge | T5: ASP (US$) | U5: Total (US$)
B6: Rack Chassis | C6: 3000 | E6: CX8 NIC | F6: =4500*2 -> 9000 | H6: B300 (2x) | I6: =+K6*2 -> 70000 | K6: 35000 | S6: 36x NVLink Male | T6: 30 | U6: =+T6*36 -> 1080
B7: Manifold (CDM) | C7: 13500 | E7: Storage | F7: =+T29+(T28*4) -> 4614.4 | H7: Cold Plate (3x) | I7: =250*3 -> 750 | O7: GB300 | P7: 71 | S7: Cables | T7: 1250 | U7: =+T7*1 -> 1250
B8: Power supply | C8: 57600 | E8: Paladin connectors | F8: =+V35 -> 333.33333 | H8: PCB (HDI) | I8: =650/0.3 -> 2166.6667 | O8: VR200 | P8: 80 | S8: Spine chassis | T8: 150 | U8: =+T8*1 -> 150
B9: Management switch | C9: =1650*2 -> 3300 | E9: NVQD (8x) | F9: =25*8 -> 200 | H9: LPDDR5X (480GB) | I9: =+T26/(1-70%) -> 8000 | S9: Total | U9: =SUM(U6:U8) -> 2480
B10: Other cooling | C10: 800 | E10: Inner Manifold | F10: 300 | H10: Assembly/Test | I10: 1120 | S10: Nvidia margin | U10: 0.7
B11: 4x Cable Cartridge | C11: =+U12 -> 33066.667 | E11: Fans (8x) | F11: =20*8 -> 160 | H11: Others | I11: 4000 | S11: ASP in BOM | U11: =+U9/(1-U10) -> 8266.6667
B12: Others | C12: 37500 | E12: Floating mount | F12: =50*2 -> 100 | S12: 4x Cable Cartridge | U12: =+U11*4 -> 33066.667
B13: Rack assembly & test | C13: 22400 | E13: Chassis | F13: 200
B14: Total | C14: =+SUM(C4:C13) -> 3994550.9 | E14: Railkit | F14: 50
E15: Assembly/Test | F15: 1600
B16: =+B3 -> GB300 NVL72 Bill of materials (US$) | E16: Others | F16: 1000
B17: =+B4 -> 18x Compute Tray | C17: =+C4/C$14 -> 0.92434903
B18: =+B5 -> 9x Switch Tray | C18: =+C5/C$14 -> 0.032800934 | E18: Switch Tray | F18: =SUM(F19:F26) -> 14558.333
B19: =+B6 -> Rack Chassis | C19: =+C6/C$14 -> 0.00075102311 | E19: Switch board | F19: =+I19 -> 11971.667 | H19: Switch board | I19: =+SUM(I20:I24) -> 11971.667
B20: =+B7 -> Manifold (CDM) | C20: =+C7/C$14 -> 0.003379604 | E20: Chassis | F20: 200 | H20: NVLink switch chip (2x) | I20: =+K21*2 -> 7200 | K20: NVLink switch chip ASP
B21: =+B8 -> Power supply | C21: =+C8/C$14 -> 0.014419644 | E21: Other cooling (includes 6x fans, etc) | F21: =150+60 -> 210 | H21: PCB (MLB) | I21: =800/(1-70%) -> 2666.6667 | K21: 3600
B22: =+B9 -> Management switch | C22: =+C9/C$14 -> 0.00082612542 | E22: Floating mount | F22: =50*2 -> 100 | H22: Cold Plate (2x) | I22: =200*2 -> 400
B23: =+B10 -> Other cooling | C23: =+C10/C$14 -> 0.00020027283 | E23: NVQD | F23: =20*18 -> 360 | H23: Assembly/Test | I23: 275
B24: =+B11 -> 4x Cable Cartridge | C24: =+C11/C$14 -> 0.0082779436 | E24: Railkit | F24: 50 | H24: Others | I24: =500+930 -> 1430
B25: =+B12 -> Others | C25: =+C12/C$14 -> 0.0093877888 | E25: Paladin connectors | F25: =+V38 -> 666.66667 | S25: Memory (ex-HBM) | T25: ASP (US$) | U25: Total (US$)
B26: =+B13 -> Rack assembly & test | C26: =+C13/C$14 -> 0.0056076392 | E26: Assembly/Test | F26: =300/(1-70%) -> 1000 | S26: 36x 480GB LPDDR5X | T26: =5*480 -> 2400 | U26: =+T26*36/(1-70%) -> 288000
B27: =+B14 -> Total | C27: =+SUM(C17:C26) -> 1 | E27: Others | F27: 600 | S27: LPDDR5X 32GB (BF3) | T27: =5*32 -> 160 | U27: =+T27*18 -> 2880
S28: E1.S NVMe SSD (7.68TB) | T28: =70*16 -> 1120 | U28: =+T28*72 -> 80640
E29: Peripheral PCB boards (90x) | F29: =+F30*90 -> 4500 | H29: ABF Substrate Content per Rack | I29: =SUM(I30:I34) -> 11160 | K29: MLCC Content per Rack | L29: =SUM(L30:L32) -> 1530 | S29: M.2 SSD (1.92TB) | T29: =70*1.92 -> 134.4 | U29: =+T29*18 -> 2419.2
E30: PCB board only ASP (US$) | F30: 50 | H30: B200 ($100 each, 72x per rack) | I30: =100*72 -> 7200 | K30: Bianca ($25 per board, 36x boards) | L30: =25*36 -> 900 | S30: Total | U30: =SUM(U26:U29) -> 373939.2
B31: Simplied GB200 NVL72 BOM | H31: Grace ($50 each, 36x per rack) | I31: =50*36 -> 1800 | K31: Switch board ($20 per board, 9x boards) | L31: =20*9 -> 180
B32: Blackwell GPU | C32: =+K6*72 -> 2520000 | H32: NVLink ($30 each, 18x per rack) | I32: =30*18 -> 540 | K32: Peripheral boards ($5 per board, 90x boards) | L32: =5*90 -> 450
B33: Grace CPU | C33: =+I5*36 -> 180000 | H33: BlueField ($30 each, 18x per rack) | I33: =30*18 -> 540
B34: NVLink Switch chip | C34: =+K21*2*9 -> 64800 | H34: CX ($30 each, 36x per rack) | I34: =30*36 -> 1080 | S34: Paladin connectors | T34: Quantity | U34: ASP (US$) | V34: Total (US$)
B35: Memory | C35: =+(I9*2+F7)*18+(T27*18) -> 373939.2 | S35: Compute tray | T35: =SUM(T36:T36) -> 4 | U35: =+V35/T35 -> 83.333333 | V35: =SUM(V36:V36) -> 333.33333
B36: PCB | C36: =(+I8*0.3*36)+(I21*0.3*9)+F29 -> 35100 | S36: 4x NVLink Female | T36: 4 | U36: 25 | V36: =+(U36*T36)/(1-70%) -> 333.33333
B37: ABF Substrate | C37: =+I29 -> 11160 | S37: Switch tray | T37: =SUM(T38) -> 8 | U37: =+V37/T37 -> 83.333333 | V37: =SUM(V38) -> 666.66667
B38: MLCC | C38: =+L29 -> 1530 | S38: 8x NVLink Female | T38: 8 | U38: 25 | V38: =+(U38*T38)/(1-70%) -> 666.66667
B39: Cooling | C39: =+((F9+F10+F11+F12)*18)+(I7*36)+(I22*9)+((F21+F22+F23)*9)+C7+C10 -> 64610 | S39: Cartridge | T39: =SUM(T40) -> 36 | U39: =+V39/T39 -> 100 | V39: =SUM(V40) -> 3600
B40: Power supply | C40: =+C8 -> 57600 | S40: 36x NVLink Male | T40: 36 | U40: 30 | V40: =+(U40*T40)/(1-70%) -> 3600
B41: Others | C41: =+C43-C42-SUM(C32:C40) -> 633811.67
B42: Markup | C42: 52000 | S42: Total | T42: =+SUM(T43:T45) -> 288 | U42: =+V42/T42 -> 91.666667 | V42: =+SUM(V43:V45) -> 26400
B43: Total | C43: =+C14 -> 3994550.9 | S43: 18x Compute tray | T43: =+T35*18 -> 72 | U43: =+U35 -> 83.333333 | V43: =+T43*U43 -> 6000
S44: 9x Switch tray | T44: =+T37*9 -> 72 | U44: =+U37 -> 83.333333 | V44: =+T44*U44 -> 6000
B45: =+B31 -> Simplied GB200 NVL72 BOM | S45: 4x Cartridge | T45: =+T39*4 -> 144 | U45: =+U39 -> 100 | V45: =+T45*U45 -> 14400
B46: =+B32 -> Blackwell GPU | C46: =+C32/C$43 -> 0.63085941
B47: =+B33 -> Grace CPU | C47: =+C33/C$43 -> 0.045061386
B48: =+B34 -> NVLink Switch chip | C48: =+C34/C$43 -> 0.016222099
B49: =+B35 -> Memory | C49: =+C35/C$43 -> 0.093612327
B50: =+B36 -> PCB | C50: =+C36/C$43 -> 0.0087869703
B51: =+B37 -> ABF Substrate | C51: =+C37/C$43 -> 0.002793806
B52: =+B38 -> MLCC | C52: =+C38/C$43 -> 0.00038302178
B53: =+B39 -> Cooling | C53: =+C39/C$43 -> 0.016174534
B54: =+B40 -> Power supply | C54: =+C40/C$43 -> 0.014419644
B55: =+B41 -> Others | C55: =+C41/C$43 -> 0.15866907
B56: =+B42 -> Markup | C56: =+C42/C$43 -> 0.013017734
B57: =+B43 -> Total | C57: =+C43/C$43 -> 1

Sheet GB200 BoM
B2: GB200 NVL72
B3: GB200 NVL72 Bill of materials (US$) | E3: Compute Tray | F3: =SUM(F4:F15) -> 169822 | P3: # of BMC
B4: 18x Compute Tray | C4: =+F3*18 -> 3056796 | E4: Compute board (2x) | F4: =+I4*2 -> 155273.33 | H4: Compute board | I4: =+SUM(I5:I11) -> 77636.667 | O4: NVL36 | P4: 41
B5: 9x Switch Tray | C5: =+F18*9 -> 126960 | E5: BF3 DPU Module | F5: 5500 | H5: Grace (1x) | I5: 5000 | K5: B200 ASP | O5: NVL72 | P5: 85 | S5: 1x Cable Cartridge | T5: ASP (US$) | U5: Total (US$)
B6: Rack Chassis | C6: 3000 | E6: CX7 NIC | F6: =1750*2 -> 3500 | H6: B200 (2x) | I6: =+K6*2 -> 60000 | K6: 30000 | S6: 36x NVLink Male | T6: 30 | U6: =+T6*36 -> 1080
B7: Manifold (CDM) | C7: 13500 | E7: Storage | F7: =+T29+(T28*4) -> 1632 | H7: Cold Plate (3x) | I7: =250*3 -> 750 | O7: GB300 | P7: 71 | S7: Cables | T7: 1250 | U7: =+T7*1 -> 1250
B8: Power supply | C8: 36000 | E8: Paladin connectors | F8: =+V35 -> 266.66667 | H8: PCB (HDI) | I8: =650/0.3 -> 2166.6667 | O8: VR200 | P8: 80 | S8: Spine chassis | T8: 150 | U8: =+T8*1 -> 150
B9: Management switch | C9: =1650*2 -> 3300 | E9: UQD (4x) | F9: =25*4 -> 100 | H9: LPDDR5X (480GB) | I9: =+T26/(1-70%) -> 5600 | S9: Total | U9: =SUM(U6:U8) -> 2480
B10: Other cooling | C10: 800 | E10: Fans (8x) | F10: =8*25 -> 200 | H10: Assembly/Test | I10: 1120 | S10: Nvidia margin | U10: 0.7
B11: 4x Cable Cartridge | C11: =+U12 -> 33066.667 | E11: Floating mount (2x) | F11: =100*2 -> 200 | H11: Others | I11: 3000 | S11: ASP in BOM | U11: =+U9/(1-U10) -> 8266.6667
B12: Others | C12: 30500 | E12: Chassis | F12: 200 | S12: 4x Cable Cartridge | U12: =+U11*4 -> 33066.667
B13: Rack assembly & test | C13: 25600 | E13: Railkit | F13: 50
B14: Total | C14: =+SUM(C4:C13) -> 3329522.7 | E14: Assembly/Test | F14: 1600
E15: Others | F15: 1300
B16: =+B3 -> GB200 NVL72 Bill of materials (US$)
B17: =+B4 -> 18x Compute Tray | C17: =+C4/C$14 -> 0.91808836
B18: =+B5 -> 9x Switch Tray | C18: =+C5/C$14 -> 0.038131592 | E18: Switch Tray | F18: =SUM(F19:F25) -> 14106.667
B19: =+B6 -> Rack Chassis | C19: =+C6/C$14 -> 0.00090103006 | E19: Switch board | F19: =+I19 -> 11613.333 | H19: Switch board | I19: =+SUM(I20:I24) -> 11613.333
B20: =+B7 -> Manifold (CDM) | C20: =+C7/C$14 -> 0.0040546353 | E20: Chassis | F20: 200 | H20: NVLink switch chip (2x) | I20: =+K21*2 -> 7200 | K20: NVLink switch chip ASP
B21: =+B8 -> Power supply | C21: =+C8/C$14 -> 0.010812361 | E21: Other cooling (includes 6x fans, etc) | F21: =150+60 -> 210 | H21: PCB (MLB) | I21: =700/(1-70%) -> 2333.3333 | K21: 3600
B22: =+B9 -> Management switch | C22: =+C9/C$14 -> 0.00099113306 | E22: Railkit | F22: 50 | H22: Cold Plate (2x) | I22: =200*2 -> 400
B23: =+B10 -> Other cooling | C23: =+C10/C$14 -> 0.00024027468 | E23: Paladin connectors | F23: =+V37 -> 533.33333 | H23: Assembly/Test | I23: 275
B24: =+B11 -> 4x Cable Cartridge | C24: =+C11/C$14 -> 0.0099313535 | E24: Assembly/Test | F24: =300/(1-70%) -> 1000 | H24: Others | I24: =475+930 -> 1405
B25: =+B12 -> Others | C25: =+C12/C$14 -> 0.0091604723 | E25: Others | F25: 500 | S25: Memory (ex-HBM) | T25: ASP (US$) | U25: Total (US$)
B26: =+B13 -> Rack assembly & test | C26: =+C13/C$14 -> 0.0076887898 | S26: 36x 480GB LPDDR5X | T26: =3.5*480 -> 1680 | U26: =+T26*36/(1-70%) -> 201600
B27: =+B14 -> Total | C27: =+SUM(C17:C26) -> 1 | E27: Peripheral PCB boards (90x) | F27: =+F28*90 -> 4500 | H27: ABF Substrate Content per Rack | I27: =SUM(I28:I32) -> 11160 | K27: MLCC Content per Rack | L27: =SUM(L28:L30) -> 1710 | S27: LPDDR5X 32GB (BF3) | T27: =3.5*32 -> 112 | U27: =+T27*18 -> 2016
E28: PCB board only ASP (US$) | F28: 50 | H28: B200 ($100 each, 72x per rack) | I28: =100*72 -> 7200 | K28: Bianca ($30 per board, 36x boards) | L28: =30*36 -> 1080 | S28: E1.S NVMe SSD (7.68TB) | T28: =50*7.68 -> 384 | U28: =+T28*72 -> 27648
H29: Grace ($50 each, 36x per rack) | I29: =50*36 -> 1800 | K29: Switch board ($20 per board, 9x boards) | L29: =20*9 -> 180 | S29: M.2 SSD (1.92TB) | T29: =50*1.92 -> 96 | U29: =+T29*18 -> 1728
H30: NVLink ($30 each, 18x per rack) | I30: =30*18 -> 540 | K30: Peripheral boards ($5 per board, 90x boards) | L30: =5*90 -> 450 | S30: Total | U30: =SUM(U26:U29) -> 232992
B31: Simplied GB200 NVL72 BOM | H31: BlueField ($30 each, 18x per rack) | I31: =30*18 -> 540
B32: Blackwell GPU | C32: =+K6*72 -> 2160000 | H32: CX ($30 each, 36x per rack) | I32: =30*36 -> 1080
B33: Grace CPU | C33: =+I5*36 -> 180000
B34: NVLink Switch chip | C34: =+K21*2*9 -> 64800 | S34: Paladin connectors | T34: Quantity | U34: ASP (US$) | V34: Total (US$)
B35: Memory | C35: =+(I9*2+F7)*18+(T27*18) -> 232992 | S35: Compute tray | T35: =SUM(T36:T36) -> 4 | U35: =+V35/T35 -> 66.666667 | V35: =SUM(V36:V36) -> 266.66667
B36: PCB | C36: =(+I8*0.3*36)+(I21*0.3*9)+F27 -> 34200 | S36: 4x NVLink Female | T36: 4 | U36: 20 | V36: =+(U36*T36)/(1-70%) -> 266.66667
B37: ABF Substrate | C37: =+I27 -> 11160 | S37: Switch tray | T37: =SUM(T38) -> 8 | U37: =+V37/T37 -> 66.666667 | V37: =SUM(V38) -> 533.33333
B38: MLCC | C38: =+L27 -> 1710 | S38: 8x NVLink Female | T38: 8 | U38: 20 | V38: =+(U38*T38)/(1-70%) -> 533.33333
B39: Cooling | C39: =+((F9+F10+F11)*18)+(I7*36)+(I22*9)+(F21*9)+C7+C10 -> 55790 | S39: Cartridge | T39: =SUM(T40) -> 36 | U39: =+V39/T39 -> 100 | V39: =SUM(V40) -> 3600
B40: Power supply | C40: =+C8 -> 36000 | S40: 36x NVLink Male | T40: 36 | U40: 30 | V40: =+(U40*T40)/(1-70%) -> 3600
B41: Others | C41: =+C43-C42-SUM(C32:C40) -> 500870.67
B42: Markup | C42: 52000 | S42: Total | T42: =+SUM(T43:T45) -> 288 | U42: =+V42/T42 -> 83.333333 | V42: =+SUM(V43:V45) -> 24000
B43: Total | C43: =+C14 -> 3329522.7 | S43: 18x Compute tray | T43: =+T35*18 -> 72 | U43: =+U35 -> 66.666667 | V43: =+T43*U43 -> 4800
S44: 9x Switch tray | T44: =+T37*9 -> 72 | U44: =+U37 -> 66.666667 | V44: =+T44*U44 -> 4800
B45: =+B31 -> Simplied GB200 NVL72 BOM | S45: 4x Cartridge | T45: =+T39*4 -> 144 | U45: =+U39 -> 100 | V45: =+T45*U45 -> 14400
B46: =+B32 -> Blackwell GPU | C46: =+C32/C$43 -> 0.64874164
B47: =+B33 -> Grace CPU | C47: =+C33/C$43 -> 0.054061803
B48: =+B34 -> NVLink Switch chip | C48: =+C34/C$43 -> 0.019462249
B49: =+B35 -> Memory | C49: =+C35/C$43 -> 0.069977598
B50: =+B36 -> PCB | C50: =+C36/C$43 -> 0.010271743
B51: =+B37 -> ABF Substrate | C51: =+C37/C$43 -> 0.0033518318
B52: =+B38 -> MLCC | C52: =+C38/C$43 -> 0.00051358713
B53: =+B39 -> Cooling | C53: =+C39/C$43 -> 0.016756156
B54: =+B40 -> Power supply | C54: =+C40/C$43 -> 0.010812361
B55: =+B41 -> Others | C55: =+C41/C$43 -> 0.15043318
B56: =+B42 -> Markup | C56: =+C42/C$43 -> 0.015617854
B57: =+B43 -> Total | C57: =+C43/C$43 -> 1
